Workbook

Sheet Resumen
A1: Fuente de alimentación multisalida para laboratorio — Documentación inicial
A2: Universidad Tecnológica de Pereira · Ingeniería Mecatrónica · Autor: Ronaldo
A4: Resultados clave
A5: Potencia máxima total de salida | B5: =Calculos!$C$20 -> 151.9 | C5: W
A6: Potencia al bus VIN DC (con pérdidas) | B6: =Calculos!$C$22 -> 176.74534 | C6: W
A7: Transformador seleccionado | B7: Antek AS-4220 — 400 VA, 2 × 20 V / 10 A en paralelo
A8: Uso del transformador (corriente RMS requerida / nominal) | B8: =Calculos!$C$79 -> 0.73981996
A9: Bus VIN DC — mínimo (peor caso) | B9: =Calculos!$C$52 -> 20.717891 | C9: V
A10: Bus VIN DC — mínimo requerido | B10: =Calculos!$C$59 -> 17.892967 | C10: V
A11: Bus VIN DC — máximo (peor caso) | B11: =Calculos!$C$63 -> 30.801643 | C11: V
A12: Capacitancia del filtro | B12: =Calculos!$C$49 -> 30000 | C12: µF
A13: Eficiencia total (red → salidas) | B13: =Calculos!$C$139 -> 0.74067202
A14: Potencia tomada de la red | B14: =Calculos!$C$138 -> 205.08403 | C14: W
A16: Índice de hojas
A17: =HYPERLINK("#Especificaciones!A1","Especificaciones") -> Especificaciones | B17: Datos cuantitativos y de topología (docente + decisiones)
A18: =HYPERLINK("#Req_Funcionales!A1","Req_Funcionales") -> Req_Funcionales | B18: Qué debe hacer el sistema
A19: =HYPERLINK("#Req_NoFuncionales!A1","Req_NoFuncionales") -> Req_NoFuncionales | B19: Cómo debe comportarse: seguridad, eficiencia, térmico, documentación
A20: =HYPERLINK("#Restricciones!A1","Restricciones") -> Restricciones | B20: Condiciones impuestas que limitan el diseño
A21: =HYPERLINK("#Lista_Componentes!A1","Lista_Componentes") -> Lista_Componentes | B21: Lista preliminar de componentes principales con fuente y estado
A22: =HYPERLINK("#Calculos!A1","Calculos") -> Calculos | B22: Cálculo del transformador, bus, rectificador, protecciones, ajuste y pistas
A23: =HYPERLINK("#Convertidores!A1","Convertidores") -> Convertidores | B23: Diseño de los cinco convertidores DC/DC por salida
A24: =HYPERLINK("#Decisiones!A1","Decisiones") -> Decisiones | B24: Datos pendientes del PDF Pag_9 con su decisión
A26: Leyenda de colores
A27: Texto azul con fondo amarillo | B27: Dato de entrada o supuesto: se puede editar y todo se recalcula.
A28: Texto negro | B28: Fórmula calculada.
A29: Texto verde | B29: Vínculo a otra hoja del libro.
A30: Fondo verde claro | B30: Resultado clave.
A32: Supuestos que conviene confirmar con el docente
A33: • Red de 120 V / 60 Hz con variación de ±10 %.
A34: • Las cinco salidas pueden estar a su corriente máxima al mismo tiempo (peor caso).
A35: • La etapa de red (IEC, fusible, interruptor, NTC, varistor) se cablea en el chasis; la PCB solo recibe el secundario.
A36: • GND común de las salidas, flotante respecto a tierra de protección.
A37: • La construcción física y las pruebas se confirman aparte (PDF §4.2).

Sheet Especificaciones
A1: Especificaciones del proyecto — datos cuantitativos y de topología
A2: Parte A y B: datos dados por el docente. Parte C: valores definidos o calculados en este diseño (vinculados a la hoja Calculos).
A3: N.º | B3: Tipo de salida | C3: Tensión (V) | D3: Corriente máx. (A) | E3: Potencia máx. (W) | F3: Convertidor DC/DC asignado | G3: Origen
A4: 1 | B4: Fija positiva | C4: 12 | D4: 5 | E4: =ABS(C4)*D4 -> 60 | F4: LM2678T-12 (reductor) | G4: Docente (PDF Tabla 1 y Tabla 3); convertidor: candidato validado
A5: 2 | B5: Fija positiva | C5: 5 | D5: 5 | E5: =ABS(C5)*D5 -> 25 | F5: LM2678T-5.0 (reductor) | G5: Docente (PDF Tabla 1 y Tabla 3); convertidor: candidato validado
A6: 3 | B6: Fija positiva | C6: 3.3 | D6: 3 | E6: =ABS(C6)*D6 -> 9.9 | F6: LM2678T-3.3 (reductor) | G6: Docente (PDF Tabla 1 y Tabla 3); convertidor: candidato validado
A7: 4 | B7: Fija negativa | C7: -12 | D7: 1 | E7: =ABS(C7)*D7 -> 12 | F7: TPS54560B (buck-boost inversor) | G7: Docente (PDF Tabla 1 y Tabla 3); convertidor: candidato validado
A8: 5 | B8: Variable 1,25–15 V (se toma 15 V para la potencia máxima) | C8: 15 | D8: 3 | E8: =ABS(C8)*D8 -> 45 | F8: LM2678T-ADJ (reductor ajustable) | G8: Docente (PDF Tabla 1 y Tabla 3); convertidor: candidato validado
B9: Potencia máxima total de salida (sin pérdidas) | E9: =SUM(E4:E8) -> 151.9 | G9: Debe coincidir con 151,9 W del PDF
A11: ID | B11: Parámetro | C11: Valor | D11: Unidad | E11: Estado | F11: Detalle | G11: Origen
A12: B. Topología y etapa de entrada (dados por el docente)
A13: ESP-01 | B13: Fuente de energía | C13: Red AC monofásica | E13: Dado | F13: A través de un transformador AC comercial. | G13: Docente (PDF Tabla 2)
A14: ESP-02 | B14: Rectificación | C14: Puente de diodos | E14: Dado | F14: GBJ3510 (35 A / 1000 V). | G14: Docente (PDF Tabla 2)
A15: ESP-03 | B15: Filtrado | C15: Capacitivo | E15: Dado | F15: 3 × 10 000 µF / 50 V en paralelo. | G15: Docente (PDF Tabla 2)
A16: ESP-04 | B16: Conversión | C16: DC/DC integrada en la PCB | E16: Dado | F16: Cinco convertidores independientes, uno por salida, desde el bus VIN DC. | G16: Docente (PDF Tabla 2, §6)
A17: ESP-05 | B17: Protecciones | C17: En tres niveles | E17: Dado | F17: Entrada (antes del transformador), bus DC (después del filtro) y una por cada salida. | G17: Docente (PDF §6)
A18: C. Valores definidos en este diseño (vinculados a la hoja Calculos)
A19: ESP-06 | B19: Tensión nominal de la red | C19: =Calculos!$C$5 -> 120 | D19: V rms | E19: Por confirmar | F19: Red de Colombia. Confirmar con el docente. | G19: Supuesto
A20: ESP-07 | B20: Frecuencia de la red | C20: =Calculos!$C$6 -> 60 | D20: Hz | E20: Por confirmar | G20: Supuesto
A21: ESP-08 | B21: Transformador | C21: Antek AS-4220 | E21: Definido | F21: Toroidal 400 VA, 2 × 20 V/10 A (en paralelo: 20 V / 20 A), primario dual 115/230 V, 50/60 Hz. | G21: Selección (hoja Calculos §5)
A22: ESP-09 | B22: Potencia de entrada al bus VIN DC (con pérdidas) | C22: =Calculos!$C$22 -> 176.74534 | D22: W | E22: Calculado | F22: Todas las salidas a su corriente máxima a la vez. | G22: Cálculo (hoja Convertidores)
A23: ESP-10 | B23: Potencia total tomada de la red | C23: =Calculos!$C$138 -> 205.08403 | D23: W | E23: Calculado | F23: Incluye pérdidas del puente y del transformador. | G23: Cálculo (hoja Calculos §10)
A24: ESP-11 | B24: Corriente DC máxima del bus | C24: =Calculos!$C$45 -> 8.2202218 | D24: A | E24: Calculado | F24: Peor caso: red −10 %, plena carga. | G24: Cálculo (hoja Calculos §4)
A25: ESP-12 | B25: Tensión MÍNIMA del bus VIN DC | C25: =Calculos!$C$52 -> 20.717891 | D25: V | E25: Calculado | F25: Debe ser ≥ mínimo requerido (ver ESP-13). | G25: Cálculo (hoja Calculos §4)
A26: ESP-13 | B26: Tensión mínima requerida del bus | C26: =Calculos!$C$59 -> 17.892967 | D26: V | E26: Calculado | F26: Para que el LM2678-12 regule y la salida variable llegue a 15 V. | G26: Cálculo (hoja Calculos §4)
A27: ESP-14 | B27: Tensión MÁXIMA del bus VIN DC | C27: =Calculos!$C$63 -> 30.801643 | D27: V | E27: Calculado | F27: Red +10 %, sin carga. Límite de los LM2678: 40 V. | G27: Cálculo (hoja Calculos §4)
A28: ESP-15 | B28: Rizado admisible del bus (pico a pico) | C28: =Calculos!$C$40 -> 3 | D28: V | E28: Definido | F28: Dato pendiente del PDF resuelto. | G28: Decisión de diseño
A29: ESP-16 | B29: Rizado real del bus (pico a pico) | C29: =Calculos!$C$51 -> 2.283395 | D29: V | E29: Calculado | F29: Con 30 000 µF a plena carga. | G29: Cálculo (hoja Calculos §4)
A30: ESP-17 | B30: Capacitancia total del bus | C30: =Calculos!$C$49 -> 30000 | D30: µF | E30: Definido | F30: 3 × 10 000 µF / 50 V. | G30: Cálculo (hoja Calculos §4)
A31: ESP-18 | B31: Tolerancia de regulación de cada salida | C31: =Calculos!$C$12 -> 0.03 | D31: ±% | E31: Definido | F31: ±2 % a 25 °C, ±3 % en temperatura. | G31: Hoja de datos LM2678
A32: ESP-19 | B32: Rizado máximo de cada salida | C32: =Calculos!$C$13 -> 0.01 | D32: % de Vout | E32: Definido | F32: Pico a pico. | G32: Hoja de datos LM2678 §7.1.3
A33: ESP-20 | B33: Eficiencia total (red → salidas) | C33: =Calculos!$C$139 -> 0.74067202 | E33: Calculado | F33: Objetivo ≥ 70 %. | G33: Cálculo (hoja Calculos §10)
A34: ESP-21 | B34: Referencia común (tierra) | C34: GND común | E34: Definido | F34: Las cinco salidas comparten GND; aislado de la red por el transformador; chasis a PE. | G34: Decisión de diseño
A35: ESP-22 | B35: Condiciones ambientales de diseño | C35: =Calculos!$C$10 -> 40 | D35: °C | E35: Definido | F35: Temperatura interna del gabinete; Tj ≤ 125 °C. | G35: Supuesto de diseño

Sheet Req_Funcionales
A1: Requerimientos funcionales — qué debe hacer el sistema
A2: Cada fila es un requisito independiente (viñeta). «Valor de diseño» se vincula con la hoja Calculos / Convertidores; «Estado» se evalúa automáticamente.
A3: ID | B3: Requisito | C3: Umbral | D3: Unidad | E3: Valor de diseño | F3: Estado | G3: Método de verificación | H3: Origen / referencia
A4: A. Etapa de entrada y bus VIN DC
A5: RF-01 | B5: La fuente debe tomar la energía de la red AC monofásica a través de un transformador comercial. | C5: — | E5: — | F5: Por inspección | G5: Inspección | H5: Docente (PDF §2.1, §4.2)
A6: RF-02 | B6: El transformador AC debe reducir la tensión de la red y aislar galvánicamente las salidas. | C6: — | E6: — | F6: Por inspección | G6: Inspección | H6: Docente (PDF §2.1)
A7: RF-03 | B7: La tensión alterna del secundario debe rectificarse con un puente de diodos de onda completa. | C7: — | E7: — | F7: Por inspección | G7: Inspección | H7: Docente (PDF §2.1, §5.1)
A8: RF-04 | B8: El filtrado capacitivo debe mantener el rizado del bus VIN DC por debajo del límite en el peor caso (plena carga, red −10 %). | C8: =Calculos!$C$40 -> 3 | D8: V pp | E8: =Calculos!$C$51 -> 2.283395 | F8: =IF(E8<=C8,"Cumple","NO CUMPLE") -> Cumple | G8: Cálculo (hoja Calculos §4) | H8: Docente (PDF §2.1) + decisión de diseño
A9: RF-05 | B9: El bus VIN DC debe mantenerse por encima de la tensión mínima requerida en el peor caso, para que la salida variable llegue a 15 V y el convertidor de +12 V regule. | C9: =Calculos!$C$59 -> 17.892967 | D9: V | E9: =Calculos!$C$52 -> 20.717891 | F9: =IF(E9>=C9,"Cumple","NO CUMPLE") -> Cumple | G9: Cálculo (hoja Calculos §4) | H9: Docente (PDF §4.2: bus con margen > 15 V)
A10: RF-06 | B10: El bus VIN DC no debe superar la tensión máxima de entrada de los convertidores con red +10 % y sin carga. | C10: =Calculos!$C$64 -> 40 | D10: V | E10: =Calculos!$C$63 -> 30.801643 | F10: =IF(E10<=C10,"Cumple","NO CUMPLE") -> Cumple | G10: Cálculo (hoja Calculos §4) | H10: Hoja de datos LM2678
A11: RF-07 | B11: El transformador debe poder entregar la corriente RMS que exige el rectificador con filtro capacitivo a plena carga. | C11: =Calculos!$C$73 -> 14.796399 | D11: A rms | E11: =Calculos!$C$30 -> 20 | F11: =IF(E11>=C11,"Cumple","NO CUMPLE") -> Cumple | G11: Cálculo (hoja Calculos §5) | H11: Decisión de diseño
A12: B. Salidas reguladas (cada una con su convertidor DC/DC)
A13: RF-08 | B13: Entregar una salida fija de +12 V con corriente máxima de 5 A. | C13: 5 | D13: A | E13: =Convertidores!$C$44 -> 5.1022119 | F13: =IF(E13>=C13,"Cumple","NO CUMPLE") -> Cumple | G13: Prueba con carga electrónica | H13: Docente (PDF Tabla 1)
A14: RF-09 | B14: Entregar una salida fija de +5 V con corriente máxima de 5 A. | C14: 5 | D14: A | E14: =Convertidores!$D$44 -> 5.3553575 | F14: =IF(E14>=C14,"Cumple","NO CUMPLE") -> Cumple | G14: Prueba con carga electrónica | H14: Docente (PDF Tabla 1)
A15: RF-10 | B15: Entregar una salida fija de +3,3 V con corriente máxima de 3 A. | C15: 3 | D15: A | E15: =Convertidores!$E$44 -> 5.4586263 | F15: =IF(E15>=C15,"Cumple","NO CUMPLE") -> Cumple | G15: Prueba con carga electrónica | H15: Docente (PDF Tabla 1)
A16: RF-11 | B16: Entregar una salida fija negativa de −12 V con corriente máxima de 1 A (convertidor inversor). | C16: 1 | D16: A | E16: =Convertidores!$F$44 -> 2.9838782 | F16: =IF(E16>=C16,"Cumple","NO CUMPLE") -> Cumple | G16: Prueba con carga electrónica | H16: Docente (PDF Tabla 1)
A17: RF-12 | B17: Entregar una salida variable con corriente máxima de 3 A. | C17: 3 | D17: A | E17: =Convertidores!$G$44 -> 5.433495 | F17: =IF(E17>=C17,"Cumple","NO CUMPLE") -> Cumple | G17: Prueba con carga electrónica | H17: Docente (PDF Tabla 1)
A18: RF-13 | B18: La salida variable debe poder ajustarse hasta su valor mínimo de 1,25 V. | C18: 1.25 | D18: V | E18: =Calculos!$C$132 -> 1.2491511 | F18: =IF(E18<=C18,"Cumple","NO CUMPLE") -> Cumple | G18: Medición con multímetro | H18: Docente (PDF Tabla 1)
A19: RF-14 | B19: La salida variable debe poder ajustarse hasta cerca de 15 V (dentro de 2 %). | C19: 14.7 | D19: V | E19: =Calculos!$C$133 -> 14.890639 | F19: =IF(E19>=C19,"Cumple","NO CUMPLE") -> Cumple | G19: Medición con multímetro | H19: Docente (PDF Tabla 1)
A20: RF-15 | B20: El ajuste de la salida variable debe hacerse con un potenciómetro multivuelta accesible. | C20: — | E20: — | F20: Por inspección | G20: Inspección | H20: Decisión de diseño
A21: RF-16 | B21: Las cinco salidas deben ser alimentadas por cinco convertidores DC/DC independientes conectados en paralelo al bus VIN DC. | C21: — | E21: — | F21: Por inspección | G21: Inspección | H21: Docente (PDF §6)
A22: RF-17 | B22: Las cinco salidas deben compartir una referencia común (GND). | C22: — | E22: — | F22: Por inspección | G22: Inspección | H22: Decisión de diseño (PDF §9)
A23: RF-18 | B23: Todas las salidas deben poder entregar su corriente máxima al mismo tiempo (diseño de peor caso). | C23: =Calculos!$C$19 -> 151.9 | D23: W | E23: =Calculos!$C$20 -> 151.9 | F23: =IF(E23>=C23,"Cumple","NO CUMPLE") -> Cumple | G23: Prueba a plena carga | H23: Decisión de diseño (PDF §9)
A24: RF-19 | B24: Cada convertidor debe limitar su corriente y apagarse por sobretemperatura (protección integrada en el IC). | C24: — | E24: — | F24: Por inspección | G24: Inspección (hoja de datos) y prueba de cortocircuito | H24: Hoja de datos LM2678 / TPS54560B
A25: C. Protecciones, maniobra y conexión
A26: RF-20 | B26: Debe existir un interruptor general de encendido en la entrada de red. | C26: — | E26: — | F26: Por inspección | G26: Inspección | H26: Decisión de diseño
A27: RF-21 | B27: Protección de entrada (antes del transformador): fusible de acción lenta, varistor contra sobretensiones y NTC limitador de arranque. | C27: =Calculos!$C$92 -> 3.4265346 | D27: A | E27: =Calculos!$C$93 -> 4 | F27: =IF(E27>=C27,"Cumple","NO CUMPLE") -> Cumple | G27: Cálculo (hoja Calculos §6) | H27: Docente (PDF §6)
A28: RF-22 | B28: Protección del bus DC (después del filtrado): fusible, TVS y resistor de sangrado. | C28: =Calculos!$C$117 -> 10.960296 | D28: A | E28: =Calculos!$C$118 -> 15 | F28: =IF(E28>=C28,"Cumple","NO CUMPLE") -> Cumple | G28: Cálculo (hoja Calculos §8) | H28: Docente (PDF §6)
A29: RF-23 | B29: Protección independiente en cada salida regulada: PTC reiniciable y diodo de sujeción (TVS o Zener). | C29: — | E29: — | F29: Por inspección | G29: Inspección y prueba de sobrecarga | H29: Docente (PDF §6)
A30: RF-24 | B30: Cada salida debe terminar en bornes (binding posts) de 15 A, un positivo por salida más bornes de GND común. | C30: 5 | D30: A | E30: 15 | F30: =IF(E30>=C30,"Cumple","NO CUMPLE") -> Cumple | G30: Inspección | H30: Docente (PDF §8.1)

Sheet Req_NoFuncionales
A1: Requerimientos no funcionales — cómo debe comportarse el sistema
A2: Seguridad, confiabilidad, eficiencia, regulación, térmico y documentación. Cada fila es un requisito independiente.
A3: ID | B3: Requisito | C3: Umbral | D3: Unidad | E3: Valor de diseño | F3: Estado | G3: Método de verificación | H3: Origen / referencia
A4: A. Seguridad
A5: RNF-01 | B5: Aislamiento galvánico entre la red y todas las salidas (primario–secundario). | C5: 1500 | D5: V | E5: =Calculos!$C$36 -> 3500 | F5: =IF(E5>=C5,"Cumple","NO CUMPLE") -> Cumple | G5: Hoja de datos (prueba del fabricante) | H5: IEC 61010-1 (referencia, confirmar) / Antek AS-4220
A6: RNF-02 | B6: Todas las tensiones accesibles deben ser extra-bajas (< 60 V DC). | C6: 60 | D6: V | E6: =Calculos!$C$63 -> 30.801643 | F6: =IF(E6<=C6,"Cumple","NO CUMPLE") -> Cumple | G6: Cálculo (hoja Calculos §4) | H6: Buena práctica de seguridad
A7: RNF-03 | B7: El chasis metálico debe conectarse a tierra de protección (PE) mediante la entrada IEC; el GND de las salidas queda flotante, con puente opcional al chasis. | C7: — | E7: — | F7: Por inspección | G7: Inspección | H7: Decisión de diseño
A8: RNF-04 | B8: Las protecciones deben dimensionarse sin usar el fusible por encima del 75 % de su corriente nominal. | C8: 0.75 | E8: =Calculos!$C$17 -> 0.75 | F8: =IF(E8<=C8,"Cumple","NO CUMPLE") -> Cumple | G8: Inspección de cálculos | H8: Buena práctica de diseño
A9: RNF-05 | B9: Los capacitores del bus deben tener tensión nominal ≥ 1,25 × la tensión máxima del bus. | C9: 1.25 | D9: × | E9: =Calculos!$C$68 -> 1.62329 | F9: =IF(E9>=C9,"Cumple","NO CUMPLE") -> Cumple | G9: Cálculo (hoja Calculos §4) | H9: Buena práctica de diseño
A10: B. Desempeño eléctrico
A11: RNF-06 | B11: Regulación de cada salida dentro de ±3 % en todo el rango de carga y temperatura. | C11: 0.03 | D11: ±% | E11: =Calculos!$C$12 -> 0.03 | F11: =IF(E11<=C11,"Cumple","NO CUMPLE") -> Cumple | G11: Prueba con carga electrónica | H11: Hoja de datos LM2678 (decisión de diseño)
A12: RNF-07 | B12: Rizado pico a pico de cada salida ≤ 1 % de su tensión nominal. | C12: =Calculos!$C$13 -> 0.01 | D12: % de Vout | E12: =MAX(Convertidores!C52:G52) -> 0.0094714211 | F12: =IF(E12<=C12,"Cumple","NO CUMPLE") -> Cumple | G12: Cálculo y medición con osciloscopio (20 MHz) | H12: Decisión de diseño (PDF §9)
A13: RNF-08 | B13: Eficiencia total (red → salidas) a plena carga. | C13: =Calculos!$C$140 -> 0.7 | E13: =Calculos!$C$139 -> 0.74067202 | F13: =IF(E13>=C13,"Cumple","NO CUMPLE") -> Cumple | G13: Cálculo (hoja Calculos §10) y prueba | H13: Decisión de diseño (PDF §9)
A14: RNF-09 | B14: Eficiencia combinada de la etapa DC/DC ≥ 80 %. | C14: 0.8 | E14: =Calculos!$C$23 -> 0.85942861 | F14: =IF(E14>=C14,"Cumple","NO CUMPLE") -> Cumple | G14: Cálculo | H14: Decisión de diseño
A15: RNF-10 | B15: El transformador no debe operar por encima del 83 % de su capacidad de corriente (margen del 20 %). | C15: =1/(1+Calculos!$C$75) -> 0.83333333 | E15: =Calculos!$C$79 -> 0.73981996 | F15: =IF(E15<=C15,"Cumple","NO CUMPLE") -> Cumple | G15: Cálculo (hoja Calculos §5) | H15: Decisión de diseño
A16: RNF-11 | B16: Recuperación suave tras un cortocircuito en cada salida (sin histéresis del límite de corriente). | C16: — | E16: — | F16: Por prueba | G16: Prueba de cortocircuito (hoja de datos LM2678 §7.1.7) | H16: Hoja de datos LM2678
A17: C. Térmico y confiabilidad
A18: RNF-12 | B18: Temperatura de unión de los convertidores ≤ 125 °C con 40 °C de ambiente interno. | C18: =Calculos!$C$11 -> 125 | D18: °C | E18: =MAX(Convertidores!C76:G76) -> 112 | F18: =IF(E18<=C18,"Cumple","NO CUMPLE") -> Cumple | G18: Cálculo (hoja Convertidores §9) y prueba térmica | H18: Hoja de datos
A19: RNF-13 | B19: El puente rectificador debe llevar disipador con resistencia térmica suficiente. | C19: =Calculos!$C$113 -> 3.6001607 | D19: °C/W | E19: =Calculos!$C$114 -> 3 | F19: =IF(E19<=C19,"Cumple","NO CUMPLE") -> Cumple | G19: Cálculo (hoja Calculos §7) | H19: Hoja de datos GBJ3510
A20: RNF-14 | B20: Vida útil de los electrolíticos del bus ≥ 5000 h a 105 °C. | C20: 5000 | D20: h | E20: 5000 | F20: =IF(E20>=C20,"Cumple","NO CUMPLE") -> Cumple | G20: Hoja de datos | H20: Nichicon LKS1H103MESB
A21: RNF-15 | B21: Pistas de potencia dimensionadas por IPC-2221 con elevación de temperatura ≤ 20 °C. | C21: 20 | D21: °C | E21: =Calculos!$C$146 -> 20 | F21: =IF(E21<=C21,"Cumple","NO CUMPLE") -> Cumple | G21: Cálculo (hoja Calculos §11) | H21: IPC-2221
A22: RNF-16 | B22: Disipación de calor total compatible con el gabinete (se requiere ventilación natural o forzada). | C22: — | D22: W | E22: =Calculos!$C$142 -> 53.184027 | F22: Por inspección | G22: Inspección / prueba térmica | H22: Cálculo (hoja Calculos §10)
A23: D. Documentación, trazabilidad y diseño de la PCB
A24: RNF-17 | B24: Cada componente debe registrarse con su fuente, enlace y características principales. | C24: — | E24: — | F24: Por inspección | G24: Inspección (hoja Lista_Componentes) | H24: Docente (PDF §8.2)
A25: RNF-18 | B25: Cada componente debe tener símbolo, huella y modelo 3D descargables de fuentes reconocidas (TI, DigiKey, Ultra Librarian, SnapEDA). | C25: — | E25: — | F25: Por inspección | G25: Inspección | H25: Docente (PDF §3.2, §8.3)
A26: RNF-19 | B26: Los componentes deben conseguirse en el mercado local o por importación (DigiKey/Mouser). | C26: — | E26: — | F26: Por inspección | G26: Inspección | H26: Docente (PDF §4.2)
A27: RNF-20 | B27: El layout debe seguir la guía de TI (AN-1229): lazos de corriente AC cortos, planos de tierra amplios y cobre de 2 oz. | C27: — | E27: — | F27: Por inspección | G27: Inspección | H27: Hoja de datos LM2678 §7.4
A28: RNF-21 | B28: Debe haber puntos de prueba y serigrafía legible en cada salida; fusibles accesibles para reemplazo. | C28: — | E28: — | F28: Por inspección | G28: Inspección | H28: Decisión de diseño

Sheet Restricciones
A1: Restricciones de diseño — condiciones impuestas que limitan las decisiones
A2: Las restricciones B se derivan de las hojas de datos de los componentes seleccionados; se verifican contra los cálculos.
A3: ID | B3: Requisito | C3: Umbral | D3: Unidad | E3: Valor de diseño | F3: Estado | G3: Método de verificación | H3: Origen / referencia
A4: A. Restricciones impuestas por el docente (PDF §4.2)
A5: RD-01 | B5: La energía de entrada viene de la red AC mediante un transformador comercial; su capacidad limita la potencia total disponible. | C5: =Calculos!$C$26 -> 400 | D5: VA | E5: =Calculos!$C$74 -> 295.92799 | F5: =IF(E5>=C5,"Cumple","NO CUMPLE") -> NO CUMPLE | G5: Cálculo (hoja Calculos §5) | H5: Docente (PDF §4.2)
A6: RD-02 | B6: Topología impuesta: puente de diodos, filtrado capacitivo y conversión DC/DC integrada en la PCB. | C6: — | E6: — | F6: Por inspección | G6: Inspección | H6: Docente (PDF §4.2)
A7: RD-03 | B7: Las salidas son las cinco de la Tabla 1 y ninguna puede superar su corriente máxima. | C7: — | E7: — | F7: Por inspección | G7: Inspección | H7: Docente (PDF §4.2)
A8: RD-04 | B8: La salida variable está limitada a 1,25–15 V, lo que exige un bus VIN DC con margen por encima de 15 V. | C8: =Calculos!$C$59 -> 17.892967 | D8: V | E8: =Calculos!$C$52 -> 20.717891 | F8: =IF(E8>=C8,"Cumple","NO CUMPLE") -> Cumple | G8: Cálculo (hoja Calculos §4) | H8: Docente (PDF §4.2)
A9: RD-05 | B9: Los elementos deben ser comerciales, con documentación del fabricante y con modelos descargables para la PCB. | C9: — | E9: — | F9: Por inspección | G9: Inspección | H9: Docente (PDF §4.2)
A10: RD-06 | B10: Los elementos deben poder conseguirse en el medio local o por importación (restricción válida del proyecto). | C10: — | E10: — | F10: Por inspección | G10: Inspección | H10: Docente (PDF §4.2)
A11: RD-07 | B11: No se diseña el transformador: se selecciona un transformador comercial. | C11: — | E11: — | F11: Por inspección | G11: Inspección | H11: Docente (PDF §4.2)
A12: RD-08 | B12: La construcción física y las pruebas de la fuente se confirmarán con el docente. | C12: — | E12: — | F12: Por inspección | G12: Inspección | H12: Docente (PDF §4.2)
A13: B. Restricciones derivadas de los componentes elegidos
A14: RD-09 | B14: LM2678-12 exige tensión de entrada ≥ 15 V. | C14: 15 | D14: V | E14: =Calculos!$C$52 -> 20.717891 | F14: =IF(E14>=C14,"Cumple","NO CUMPLE") -> Cumple | G14: Cálculo | H14: Hoja de datos LM2678 §5.7
A15: RD-10 | B15: Los LM2678 admiten como máximo 40 V de entrada en operación (45 V absolutos). | C15: 40 | D15: V | E15: =Calculos!$C$63 -> 30.801643 | F15: =IF(E15<=C15,"Cumple","NO CUMPLE") -> Cumple | G15: Cálculo | H15: Hoja de datos LM2678 §5.3
A16: RD-11 | B16: TPS54560B: la tensión vista por el IC (Vin + |Vout|) no debe superar 60 V. | C16: 60 | D16: V | E16: =Convertidores!$F$19 -> 42.801643 | F16: =IF(E16<=C16,"Cumple","NO CUMPLE") -> Cumple | G16: Cálculo (hoja Convertidores §2) | H16: Hoja de datos TPS54560B
A17: RD-12 | B17: Ciclo de trabajo máximo del LM2678: 91 %. | C17: 0.91 | E17: =MAX(Convertidores!C27:E27,Convertidores!G27) -> 0.74312404 | F17: =IF(E17<=C17,"Cumple","NO CUMPLE") -> Cumple | G17: Cálculo (hoja Convertidores §3) | H17: Hoja de datos LM2678 §5.9
A18: RD-13 | B18: Con Vout > 6 V y D > 50 % el fabricante recomienda cargas ≤ I_lim/2 para evitar histéresis del límite de corriente (aplica a +12 V y a la variable en 15 V). Riesgo conocido: validar con prueba de cortocircuito y, si aparece, reducir Cout de la variable. | C18: =Convertidores!G43/2 -> 2.875 | D18: A | E18: =Convertidores!$G$9 -> 3 | F18: =IF(E18<=C18,"Cumple","REVISAR EN PRUEBA") -> REVISAR EN PRUEBA | G18: Prueba de cortocircuito | H18: Hoja de datos LM2678 §7.1.7
A19: RD-14 | B19: Disipadores de los LM2678 (TO-220): resistencia térmica ≤ la mínima requerida entre las cuatro salidas. | C19: =MIN(Convertidores!C73:E73,Convertidores!G73) -> 18.25 | D19: °C/W | E19: =Convertidores!$C$74 -> 12 | F19: =IF(E19<=C19,"Cumple","NO CUMPLE") -> Cumple | G19: Cálculo (hoja Convertidores §9) | H19: Hoja de datos LM2678 §5.4
A20: RD-15 | B20: La corriente de rizado RMS por capacitor del bus no debe exceder la nominal del capacitor elegido (validar en la hoja de datos). | C20: — | D20: A rms | E20: =Calculos!$C$84 -> 4.1009672 | F20: Por inspección | G20: Inspección (hoja de datos del capacitor) | H20: Cálculo (hoja Calculos §5)
A21: RD-16 | B21: Los cuatro LM2678 comparten el bus: se usa cobre de 2 oz y un plano de tierra continuo (recomendación del fabricante). | C21: — | E21: — | F21: Por inspección | G21: Inspección | H21: Hoja de datos LM2678 §7.4
A22: RD-17 | B22: La etapa de red (módulo IEC, fusible, interruptor, NTC y varistor) se cablea en el chasis; la PCB recibe solo el secundario de baja tensión. | C22: — | E22: — | F22: Por inspección | G22: Inspección | H22: Decisión de diseño (confirmar con el docente)

Sheet Lista_Componentes
A1: Lista preliminar de componentes principales
A2: Cada componente trae su función, su justificación (cálculo en las hojas Calculos / Convertidores), su fuente y el estado de verificación. Los enlaces de búsqueda de DigiKey y SnapEDA se abren con el número de parte.
A3: ID | B3: Bloque | C3: Componente | D3: Referencia (MPN) | E3: Fabricante | F3: Características clave | G3: Cant. | H3: Función | I3: Justificación / cálculo | J3: Montaje | K3: Fuente (hoja de datos / distribuidor) | L3: Modelos CAD (símbolo, huella, 3D) | M3: Estado de verificación
A4: ENTRADA DE RED (cableada en el chasis)
A5: C-01 | B5: Entrada de red | C5: Módulo IEC C14 con interruptor y portafusible | D5: Schurter DD12 (familia) | E5: Schurter | F5: IEC 60320 C14, 10 A / 250 V, interruptor, portafusible 5 × 20 mm, terminal PE | G5: 1 | H5: Conexión de red, interruptor general y soporte del fusible de entrada | I5: RF-20, RF-21; I primario máx. en Calculos §5 | J5: Chasis | K5: https://www.digikey.com/en/products/result?keywords=Schurter%20DD12 | L5: https://www.snapeda.com/search?q=Schurter%20DD12 | M5: Familia recomendada — confirmar MPN exacto
A6: C-02 | B6: Protección de entrada | C6: Fusible 5 × 20 mm, acción lenta | D6: Littelfuse 0215004.MXP | E6: Littelfuse | F6: T4A, 250 V (≥ I_prim/0,75 — ver Calculos §6) | G6: 2 | H6: Protege el primario del transformador (1 en uso + 1 repuesto) | I6: Calculos §6: fusible ≥ I_primario_max / 0,75 | J6: Chasis | K6: https://www.digikey.com/en/products/result?keywords=0215004.MXP | L6: https://www.snapeda.com/search?q=0215004.MXP | M6: Referencia estándar — validar MPN y stock
A7: C-03 | B7: Protección de entrada | C7: Varistor (MOV) 14 mm | D7: TDK EPCOS S14K150 (B72214S0151K101) | E7: TDK / EPCOS | F7: 150 V AC continuos, disco 14 mm | G7: 1 | H7: Limita sobretensiones de la red | I7: Calculos §6: V_MOV ≥ 1,1 · V_red máx. | J7: Chasis | K7: https://www.digikey.com/en/products/result?keywords=S14K150 | L7: https://www.snapeda.com/search?q=S14K150 | M7: Referencia estándar — validar MPN y stock
A8: C-04 | B8: Protección de entrada | C8: Termistor NTC limitador de arranque | D8: Ametherm SL32 10015 | E8: Ametherm | F8: 10 Ω a 25 °C, 15 A en régimen | G8: 1 | H8: Limita el pico de arranque del toroidal y de los 30 000 µF | I8: Calculos §6: pico ≈ 19 A < 20 A | J8: Chasis | K8: https://www.digikey.com/en/products/result?keywords=SL32%2010015 | L8: https://www.snapeda.com/search?q=SL32%2010015 | M8: Referencia estándar — validar MPN y stock
A9: TRANSFORMADOR AC
A10: C-05 | B10: Transformador | C10: Transformador toroidal de potencia | D10: Antek AS-4220 | E10: Antek Inc. | F10: 400 VA; primario dual 115/230 V, 50/60 Hz; 2 × 20 V / 10 A (en paralelo 20 V / 20 A); pantalla electrostática; aislamiento > 3500 V | G10: 1 | H10: Reduce y aísla la tensión de red | I10: Calculos §5: uso ≈ 74 % con 20 % de margen; AS-3220 (300 VA) queda al límite | J10: Chasis | K10: https://www.antekinc.com/as-4220-400va-20v-transformer/ | L10: Proporcionar medidas del fabricante (5,1" Ø × 3,1") | M10: Verificado en hoja de datos del fabricante
A11: RECTIFICACIÓN Y FILTRADO
A12: C-06 | B12: Rectificación | C12: Borne de tornillo para PCB (secundario AC) | D12: Phoenix Contact MKDSP 10 (paso 10,16 mm) | E12: Phoenix Contact | F12: ≥ 20 A, 2 posiciones | G12: 1 | H12: Entrada del secundario del transformador a la PCB | I12: Calculos §5: I_sec rms ≈ 15 A | J12: PCB | K12: https://www.digikey.com/en/products/result?keywords=MKDSP%2010 | L12: https://www.snapeda.com/search?q=MKDSP%2010 | M12: Familia recomendada — confirmar MPN exacto
A13: C-07 | B13: Rectificación | C13: Puente rectificador monofásico | D13: GBJ3510 | E13: Diodes Inc. | F13: 35 A (con disipador), 1000 V, VF 1,1 V @ 17,5 A, IFSM 400 A | G13: 1 | H13: Rectifica el AC del secundario | I13: Calculos §7: I ≥ 2·I_DC, V_RRM ≥ 2·V_pico | J13: PCB | K13: https://www.diodes.com/assets/Datasheets/GBJ3510.pdf | L13: https://www.snapeda.com/search?q=GBJ3510 | M13: Verificado en hoja de datos del fabricante
A14: C-08 | B14: Rectificación | C14: Disipador del puente | D14: Perfil de aluminio / fijación al chasis | E14: Genérico | F14: Rθsa ≤ 3,0 °C/W, con grasa térmica | G14: 1 | H14: Evacua ≈ 18 W del puente | I14: Calculos §7: Rθsa requerido ≈ 3,6 °C/W | J14: Chasis / PCB | K14: https://www.digikey.com/en/products/result?keywords=heat%20sink%20bridge%20rectifier%20GBJ | L14: No aplica | M14: Valor definido — validar referencia vigente
A15: C-09 | B15: Filtrado | C15: Capacitor electrolítico snap-in 10 000 µF / 50 V | D15: Nichicon LKS1H103MESB | E15: Nichicon | F15: 10 000 µF, 50 V, 105 °C, 5000 h; verificar corriente de rizado ≥ valor de Calculos §5 | G15: 3 | H15: Forma el bus VIN DC y reduce el rizado | I15: Calculos §4: C ≥ 22 900 µF; 3 × 10 000 µF = 30 000 µF | J15: PCB | K15: https://www.newark.com/c/passive-components/capacitors/aluminium-electrolytic-capacitors?brand=nichicon&capacitance=10000uf | L15: https://www.snapeda.com/search?q=LKS1H103MESB | M15: Verificado en catálogo (fabricante/distribuidor)
A16: C-10 | B16: Filtrado | C16: Resistor de sangrado 4,7 kΩ / 2 W | D16: Genérico (película metálica) | E16: Yageo / Vishay | F16: 4,7 kΩ, 2 W, 1 % | G16: 1 | H16: Descarga los capacitores al apagar (τ ≈ 141 s) | I16: Calculos §8 | J16: PCB | K16: https://www.digikey.com/en/products/result?keywords=4.7k%202W%20resistor | L16: No aplica | M16: Referencia estándar — validar MPN y stock
A17: PROTECCIÓN DEL BUS DC
A18: C-11 | B18: Protección del bus | C18: Fusible ATO 15 A y portafusible para PCB | D18: Littelfuse 0287015.PXCN | E18: Littelfuse | F18: 15 A, 32 V, tipo ATO | G18: 2 | H18: Protege el bus VIN DC (1 en uso + 1 repuesto) | I18: Calculos §8: fusible ≥ I_DC/0,75 | J18: PCB | K18: https://www.digikey.com/en/products/result?keywords=0287015.PXCN | L18: https://www.snapeda.com/search?q=0287015.PXCN | M18: Referencia estándar — validar MPN y stock
A19: C-12 | B19: Protección del bus | C19: TVS unidireccional 1500 W | D19: Littelfuse SMCJ30A | E19: Littelfuse | F19: Vwm 30 V, Vbr 33,3–36,8 V, Vc 48,4 V | G19: 1 | H19: Recorta transitorios en el bus | I19: Calculos §8: Vbr > V_bus máx. | J19: PCB | K19: https://www.digikey.com/en/products/result?keywords=SMCJ30A | L19: https://www.snapeda.com/search?q=SMCJ30A | M19: Referencia estándar — validar MPN y stock
A20: CONVERTIDORES DC/DC
A21: C-13 | B21: +12 V / 5 A | C21: Regulador reductor 5 A, 12 V fijo | D21: LM2678T-12/NOPB | E21: Texas Instruments | F21: Vin 15–40 V, 5 A, 260 kHz, TO-220-7 | G21: 1 | H21: Genera +12 V | I21: Hoja Convertidores (columna +12 V) | J21: PCB + disipador | K21: https://www.ti.com/lit/ds/symlink/lm2678.pdf | L21: https://www.ti.com/product/LM2678 | M21: Verificado en hoja de datos del fabricante
A22: C-14 | B22: +5 V / 5 A | C22: Regulador reductor 5 A, 5 V fijo | D22: LM2678T-5.0/NOPB | E22: Texas Instruments | F22: Vin 8–40 V, 5 A, TO-220-7 | G22: 1 | H22: Genera +5 V | I22: Hoja Convertidores (columna +5 V) | J22: PCB + disipador | K22: https://www.ti.com/lit/ds/symlink/lm2678.pdf | L22: https://www.ti.com/product/LM2678 | M22: Verificado en hoja de datos del fabricante
A23: C-15 | B23: +3,3 V / 3 A | C23: Regulador reductor 5 A, 3,3 V fijo | D23: LM2678T-3.3/NOPB | E23: Texas Instruments | F23: Vin 8–40 V, 5 A, TO-220-7 | G23: 1 | H23: Genera +3,3 V | I23: Hoja Convertidores (columna +3,3 V) | J23: PCB + disipador | K23: https://www.ti.com/lit/ds/symlink/lm2678.pdf | L23: https://www.ti.com/product/LM2678 | M23: Verificado en hoja de datos del fabricante
A24: C-16 | B24: Variable / 3 A | C24: Regulador reductor 5 A, ajustable | D24: LM2678T-ADJ/NOPB | E24: Texas Instruments | F24: Vout 1,2–37 V, 5 A, TO-220-7 | G24: 1 | H24: Genera la salida variable 1,25–15 V | I24: Hoja Convertidores (columna Variable) y Calculos §9 | J24: PCB + disipador | K24: https://www.ti.com/lit/ds/symlink/lm2678.pdf | L24: https://www.ti.com/product/LM2678 | M24: Verificado en hoja de datos del fabricante
A25: C-17 | B25: −12 V / 1 A | C25: Convertidor reductor 60 V / 5 A (en configuración inversora) | D25: TPS54560BDDAR | E25: Texas Instruments | F25: Vin 4,5–60 V, 5 A, HSOIC-8 PowerPAD; configuración inversora según §8.3 del datasheet y nota SLVA317 | G25: 1 | H25: Genera −12 V a partir del bus | I25: Hoja Convertidores (columna −12 V) | J25: PCB | K25: https://www.ti.com/lit/ds/symlink/tps54560b.pdf | L25: https://www.ti.com/product/TPS54560B | M25: Verificado en hoja de datos del fabricante
A26: C-18 | B26: +12 V, +5 V, +3,3 V | C26: Inductor 22 µH, 5,22 A | D26: Renco RL-1283-22-43 (L41) | E26: Renco / Pulse | F26: 22 µH, 5,22 A, núcleo de ferrita, through-hole | G26: 3 | H26: Filtro de salida de los tres convertidores fijos | I26: Hoja Convertidores §4: L ≥ L_mín | J26: PCB | K26: https://www.ti.com/lit/ds/symlink/lm2678.pdf | L26: https://www.snapeda.com/search?q=RL-1283-22-43 | M26: Verificado en hoja de datos del fabricante (Tabla 7-3 de TI)
A27: C-19 | B27: Variable | C27: Inductor 47 µH, 3,57 A | D27: Pulse PE-54039 / Renco RL-5472-3 (L39) | E27: Pulse / Renco | F27: 47 µH, 3,57 A, through-hole | G27: 1 | H27: Filtro de salida de la variable | I27: Hoja Convertidores §4 | J27: PCB | K27: https://www.ti.com/lit/ds/symlink/lm2678.pdf | L27: https://www.snapeda.com/search?q=PE-54039 | M27: Verificado en hoja de datos del fabricante (Tabla 7-3 de TI)
A28: C-20 | B28: −12 V | C28: Inductor 33 µH, 4,26 A | D28: Pulse PE-54040 / Renco RL-1283-33-43 (L40) | E28: Pulse / Renco | F28: 33 µH, 4,26 A, through-hole | G28: 1 | H28: Inductor del convertidor inversor | I28: Hoja Convertidores §4: I_pico ≈ 1,9 A | J28: PCB | K28: https://www.ti.com/lit/ds/symlink/lm2678.pdf | L28: https://www.snapeda.com/search?q=PE-54040 | M28: Verificado en hoja de datos del fabricante (Tabla 7-3 de TI)
A29: C-21 | B29: LM2678 (4 salidas) | C29: Diodo Schottky 7,5 A / 45 V | D29: MBR745 | E29: onsemi / Vishay | F29: 7,5 A, 45 V, TO-220 | G29: 4 | H29: Diodo de libre circulación de cada LM2678 | I29: Hoja Convertidores §8 | J29: PCB | K29: https://www.ti.com/lit/ds/symlink/lm2678.pdf | L29: https://www.snapeda.com/search?q=MBR745 | M29: Verificado en hoja de datos del fabricante (Tabla 7-4 de TI)
A30: C-22 | B30: −12 V | C30: Diodo Schottky 3 A / 60 V | D30: SS36 | E30: onsemi / Vishay | F30: 3 A, 60 V, SMA/SMC | G30: 1 | H30: Diodo del convertidor inversor (V_R = Vin + |Vout|) | I30: Hoja Convertidores §8: 60 V ≥ 1,3 · 42,8 V | J30: PCB | K30: https://www.digikey.com/en/products/result?keywords=SS36 | L30: https://www.snapeda.com/search?q=SS36 | M30: Referencia estándar — validar MPN y stock
A31: C-23 | B31: LM2678 (4 salidas) | C31: Capacitor de entrada 1500 µF / 63 V (low-ESR) | D31: Equivalente vigente a Panasonic HFQ C16 | E31: Panasonic / Nichicon / Rubycon | F31: 1500 µF, 63 V, Irms ≥ 2,5 A a 100 kHz | G31: 4 | H31: Capacitor de entrada local de cada LM2678 | I31: Hoja Convertidores §7 | J31: PCB | K31: https://www.digikey.com/en/products/result?keywords=1500uF%2063V%20low%20ESR | L31: Según MPN final | M31: Valor definido — validar referencia vigente
A32: C-24 | B32: +12 V, +5 V, Variable | C32: Capacitor de salida 560 µF / 35 V (low-ESR) | D32: Equivalente vigente a Panasonic HFQ C5 | E32: Panasonic / Nichicon / Rubycon | F32: 560 µF, 35 V, Irms ≥ 1,4 A | G32: 4 | H32: 1 en +12 V, 1 en +5 V y 2 en la variable | I32: Hoja Convertidores §6 | J32: PCB | K32: https://www.digikey.com/en/products/result?keywords=560uF%2035V%20low%20ESR | L32: Según MPN final | M32: Valor definido — validar referencia vigente
... A41: C-33 | B41: LM2678 (4 salidas) | C41: Disipador para TO-220 | D41: Disipador estándar TO-220 | E41: Aavid / Wakefield | F41: Rθsa ≤ 12 °C/W, con tornillo y grasa térmica | G41: 4 | H41: Evacua el calor de cada LM2678 | I41: Hoja Convertidores §9 | J41: PCB | K41: https://www.digikey.com/en/products/result?keywords=heat%20sink%20TO-220%2012%20C/W | L41: No aplica | M41: Valor definido — validar referencia vigente
A42: PROTECCIONES POR SALIDA Y BORNES
A43: C-34 | B43: +12 V y +5 V | C43: PTC reiniciable 7 A (retención) / 14 A (disparo) | D43: Bourns MF-R700 | E43: Bourns | F43: 7 A hold, 14 A trip, 30 V, radial | G43: 2 | H43: Protección de sobrecorriente por salida | I43: Hoja Convertidores §10 | J43: PCB | K43: https://www.bourns.com/docs/product-datasheets/mf-r.pdf | L43: https://www.digikey.com/en/products/result?keywords=MF-R700 | M43: Verificado en hoja de datos del fabricante
A44: C-35 | B44: +3,3 V y Variable | C44: PTC reiniciable 5 A / 10 A | D44: Bourns MF-R500 | E44: Bourns | F44: 5 A hold, 10 A trip, radial | G44: 2 | H44: Protección de sobrecorriente por salida | I44: Hoja Convertidores §10 | J44: PCB | K44: https://www.bourns.com/docs/product-datasheets/mf-r.pdf | L44: https://www.digikey.com/en/products/result?keywords=MF-R500 | M44: Verificado en catálogo (fabricante/distribuidor)
A45: C-36 | B45: −12 V | C45: PTC reiniciable 1,6 A / 3,2 A | D45: Bourns MF-R160 | E45: Bourns | F45: 1,6 A hold, radial | G45: 1 | H45: Protección de sobrecorriente de −12 V | I45: Hoja Convertidores §10 | J45: PCB | K45: https://www.bourns.com/docs/product-datasheets/mf-r.pdf | L45: https://www.digikey.com/en/products/result?keywords=MF-R160 | M45: Verificado en catálogo (fabricante/distribuidor)
A46: C-37 | B46: +12 V | C46: TVS 1500 W | D46: SMCJ13A | E46: Littelfuse | F46: Vwm 13 V, Vc 21,5 V | G46: 1 | H46: Sujeción de sobretensión en +12 V | I46: Hoja Convertidores §10 | J46: PCB | K46: https://www.digikey.com/en/products/result?keywords=SMCJ13A | L46: https://www.snapeda.com/search?q=SMCJ13A | M46: Referencia estándar — validar MPN y stock
A47: C-38 | B47: +5 V | C47: TVS 1500 W | D47: SMCJ6.0A | E47: Littelfuse | F47: Vwm 6 V, Vc 10,3 V | G47: 1 | H47: Sujeción de sobretensión en +5 V | I47: Hoja Convertidores §10 | J47: PCB | K47: https://www.digikey.com/en/products/result?keywords=SMCJ6.0A | L47: https://www.snapeda.com/search?q=SMCJ6.0A | M47: Referencia estándar — validar MPN y stock
A48: C-39 | B48: +3,3 V | C48: Diodo Zener 5 W | D48: 1N5335B | E48: onsemi / Microsemi | F48: 3,9 V, 5 W | G48: 1 | H48: Sujeción de sobretensión en +3,3 V (no existe TVS de 1500 W con Vwm 3,3 V) | I48: Hoja Convertidores §10 | J48: PCB | K48: https://www.digikey.com/en/products/result?keywords=1N5335B | L48: https://www.snapeda.com/search?q=1N5335B | M48: Referencia estándar — validar MPN y stock
A49: C-40 | B49: −12 V | C49: TVS bidireccional 1500 W | D49: SMCJ13CA | E49: Littelfuse | F49: Vwm ±13 V | G49: 1 | H49: Sujeción en −12 V | I49: Hoja Convertidores §10 | J49: PCB | K49: https://www.digikey.com/en/products/result?keywords=SMCJ13CA | L49: https://www.snapeda.com/search?q=SMCJ13CA | M49: Referencia estándar — validar MPN y stock
A50: C-41 | B50: Variable | C50: TVS 1500 W | D50: SMCJ16A | E50: Littelfuse | F50: Vwm 16 V, Vc 26 V | G50: 1 | H50: Sujeción en la variable (hasta 15 V) | I50: Hoja Convertidores §10 | J50: PCB | K50: https://www.digikey.com/en/products/result?keywords=SMCJ16A | L50: https://www.snapeda.com/search?q=SMCJ16A | M50: Referencia estándar — validar MPN y stock
A51: C-42 | B51: Bornes de salida | C51: Binding post rojo (positivo) | D51: Pomona 3770-2 | E51: Pomona | F51: 15 A, 2,5 kV, montaje en panel | G51: 5 | H51: Un borne positivo por salida | I51: RF-24 | J51: Panel + cable | K51: https://www.newark.com/pomona/3770-2/binding-post-15a-turret-red/dp/78B1723 | L51: https://www.snapeda.com/search?q=3770-2 | M51: Verificado en hoja de datos del fabricante
A52: C-43 | B52: Bornes de salida | C52: Binding post negro (GND) | D52: Pomona 3770-0 | E52: Pomona | F52: 15 A, 2,5 kV, montaje en panel | G52: 2 | H52: Bornes de GND común | I52: RF-17, RF-24 | J52: Panel + cable | K52: https://www.newark.com/pomona/3770-0/binding-post-turret-15a-black/dp/78Y6926 | L52: https://www.snapeda.com/search?q=3770-0 | M52: Verificado en hoja de datos del fabricante
A53: C-44 | B53: Bornes de salida | C53: Borne de tornillo para PCB (salidas) | D53: Phoenix Contact MKDSP 10 (paso 10,16 mm) | E53: Phoenix Contact | F53: ≥ 20 A, 7 posiciones (5 salidas + 2 GND) | G53: 7 | H53: Conexión de las salidas de la PCB a los bornes del panel | I53: Calculos §11: pistas de 5 A | J53: PCB | K53: https://www.digikey.com/en/products/result?keywords=MKDSP%2010 | L53: https://www.snapeda.com/search?q=MKDSP%2010 | M53: Familia recomendada — confirmar MPN exacto
A55: Total de líneas de componentes: | G55: =SUM(G4:G53) -> 83
A56: Nota: «Verificado en hoja de datos» = parámetros comprobados contra el documento del fabricante. «Referencia estándar / familia recomendada» = valores calculados y validados, pero el MPN exacto y el stock se confirman en DigiKey/Mouser antes de comprar.

Sheet Calculos
A1: Cálculos de diseño — Fuente de alimentación multisalida
A2: Todas las cifras se recalculan a partir de las celdas azules (entradas / supuestos). Celdas en negro = fórmulas. Cada fila indica la fórmula usada y su fuente. El detalle por convertidor está en la hoja «Convertidores».
A3: N.º | B3: Parámetro | C3: Valor | D3: Unidad | E3: Fórmula / fundamento | F3: Fuente / nota
A4: 1. SUPUESTOS GENERALES Y DATOS DE LA RED
A5: 1 | B5: Tensión nominal de la red | C5: 120 | D5: V rms | E5: Red monofásica de Colombia (120 V / 60 Hz). | F5: Supuesto — confirmar con el docente
A6: 2 | B6: Frecuencia de la red | C6: 60 | D6: Hz | E6: Red de Colombia. | F6: Supuesto — confirmar con el docente
A7: 3 | B7: Variación admisible de la red | C7: 0.1 | D7: ±% | E7: Se diseña para −10 % / +10 % de la tensión nominal. | F7: Supuesto de diseño
A8: 4 | B8: Tensión de red mínima | C8: =$C$5*(1-$C$7) -> 108 | D8: V rms | E8: V_red·(1 − tol)
A9: 5 | B9: Tensión de red máxima | C9: =$C$5*(1+$C$7) -> 132 | D9: V rms | E9: V_red·(1 + tol)
A10: 6 | B10: Temperatura ambiente interna del gabinete | C10: 40 | D10: °C | E10: Peor caso dentro de la caja cerrada. | F10: Supuesto de diseño
A11: 7 | B11: Temperatura de unión máxima de diseño | C11: 125 | D11: °C | E11: Límite de operación de los convertidores. | F11: Hoja de datos LM2678 (TI, SNVS029L) §5.3
A12: 8 | B12: Tolerancia de regulación de cada salida | C12: 0.03 | D12: ±% | E12: ±2 % a 25 °C y ±3 % en todo el rango de temperatura (LM2678 fijas). | F12: Hoja de datos LM2678 (TI, SNVS029L) §5.5–5.7
A13: 9 | B13: Rizado máximo de salida (pico a pico) | C13: 0.01 | D13: % de Vout | E13: Criterio del fabricante: rizado ≤ 1 % de Vout. | F13: Hoja de datos LM2678 (TI, SNVS029L) §7.1.3
A14: 10 | B14: Rizado máximo de corriente en el inductor | C14: 0.3 | D14: × Iout | E14: El inductor se elige para ΔI_L ≤ 30 % de la corriente máxima. | F14: Hoja de datos LM2678 (TI, SNVS029L) §7.1.2
A15: 11 | B15: Factor de reducción de corriente de retención del PTC | C15: 0.75 | E15: Corriente de retención disminuye con la temperatura (≈50–60 °C dentro del gabinete). | F15: Supuesto — verificar curva de derating Bourns MF-R
A16: 12 | B16: Margen sobre la corriente máxima de salida (PTC) | C16: 1.05 | D16: × | E16: La retención derateada debe superar 1,05 × Imax. | F16: Decisión de diseño
A17: 13 | B17: Factor de uso de fusibles | C17: 0.75 | E17: Un fusible no debe operar de forma continua por encima del 75 % de su corriente nominal. | F17: Práctica de diseño (hojas de datos de fusibles)
A18: 2. POTENCIA TOTAL (resumen; el detalle por salida está en la hoja Convertidores)
A19: 14 | B19: Potencia máxima total de salida (dato del docente) | C19: 151.9 | D19: W | E19: Suma de V·I máximos de las cinco salidas. | F19: Documento del proyecto (PDF) Tabla 3
A20: 15 | B20: Potencia total de salida (recalculada) | C20: =SUM(Convertidores!C10:G10) -> 151.9 | D20: W | E20: Σ |Vout|·Iout | F20: Hoja Convertidores
A21: 16 | B21: Coincidencia con el dato del docente | C21: =IF(ABS($C$20-$C$19)<0.05,"OK","REVISAR") -> OK | E21: Debe ser igual a 151,9 W.
A22: 17 | B22: Potencia de entrada al bus VIN DC (con pérdidas de los convertidores) | C22: =SUM(Convertidores!C12:G12) -> 176.74534 | D22: W | E22: Σ Pout / η de cada convertidor | F22: Hoja Convertidores
A23: 18 | B23: Eficiencia combinada de la etapa DC/DC | C23: =$C$20/$C$22 -> 0.85942861 | E23: P_out_total / P_in_DC
A24: 3. TRANSFORMADOR SELECCIONADO — DATOS DE LA HOJA DE DATOS
A25: 19 | B25: Modelo | C25: Antek AS-4220 (toroidal, con pantalla electrostática) | E25: Selección justificada en las secciones 4 y 5. | F25: Hoja de datos Antek AS-4220
A26: 20 | B26: Potencia nominal | C26: 400 | D26: VA | E26: Dato del fabricante. | F26: Hoja de datos Antek AS-4220
A27: 21 | B27: Tensión nominal de cada secundario | C27: 20 | D27: V rms | E27: Dos secundarios idénticos de 20 V. | F27: Hoja de datos Antek AS-4220
A28: 22 | B28: Corriente nominal de cada secundario | C28: 10 | D28: A rms | E28: Dato del fabricante (2 × 10 A). | F28: Hoja de datos Antek AS-4220
A29: 23 | B29: Número de secundarios conectados en paralelo | C29: 2 | E29: Los dos devanados se conectan en paralelo y en fase para 20 V / 20 A. | F29: Decisión de diseño (verificar fase con multímetro)
A30: 24 | B30: Corriente nominal con secundarios en paralelo | C30: =$C$28*$C$29 -> 20 | D30: A rms | E30: I_cada · N
A31: 25 | B31: Tensión del secundario en vacío (red 120 V, 60 Hz) | C31: 20.7 | D31: V rms | E31: Medida en la prueba de carga del fabricante. | F31: Hoja de datos Antek AS-4220 (tabla de pruebas)
A32: 26 | B32: Tensión del secundario a plena carga (18,6 A) | C32: 19.8 | D32: V rms | E32: Medida en la prueba de carga del fabricante. | F32: Hoja de datos Antek AS-4220 (tabla de pruebas)
A33: 27 | B33: Corriente de la prueba de plena carga | C33: 18.6 | D33: A rms | E33: Corriente a la que se midieron los 19,8 V. | F33: Hoja de datos Antek AS-4220 (tabla de pruebas)
A34: 28 | B34: Regulación del transformador | C34: =($C$31-$C$32)/$C$32 -> 0.045454545 | D34: % | E34: (V_vacío − V_carga) / V_carga
A35: 29 | B35: Eficiencia del transformador | C35: 0.95 | E35: Valor típico de toroidales de 300–500 VA. | F35: Supuesto de diseño
A36: 30 | B36: Aislamiento primario–secundario (prueba dieléctrica) | C36: 3500 | D36: V | E36: Aislamiento galvánico entre red y salidas. | F36: Hoja de datos Antek AS-4220
A37: 4. BUS VIN DC: RECTIFICACIÓN Y FILTRADO
A38: 31 | B38: Caída directa por diodo del puente (con corriente de pico) | C38: 1.1 | D38: V | E38: VF = 1,1 V a 17,5 A. | F38: Hoja de datos GBJ3510 (Diodes Inc.)
A39: 32 | B39: Caída directa por diodo con poca corriente (sin carga) | C39: 0.7 | D39: V | E39: Valor típico a corriente baja. | F39: Supuesto de diseño
A40: 33 | B40: Rizado admisible del bus (pico a pico, peor caso) | C40: 3 | D40: V | E40: Define la capacitancia mínima del filtro. | F40: Decisión de diseño (dato pendiente del PDF)
A41: 34 | B41: Tensión del secundario con red −10 % y plena carga | C41: =$C$32*(1-$C$7) -> 17.82 | D41: V rms | E41: V_plena_carga · (1 − tol) | F41: Peor caso para el mínimo del bus
A42: 35 | B42: Tensión de pico del secundario (red −10 %) | C42: =$C$41*SQRT(2) -> 25.201286 | D42: V | E42: V_rms · √2
A43: 36 | B43: Pico del bus tras el puente (red −10 %) | C43: =$C$42-2*$C$38 -> 23.001286 | D43: V | E43: V_pico − 2·VF (conducen dos diodos)
A44: 37 | B44: Tensión media estimada del bus (red −10 %) | C44: =$C$43-$C$40/2 -> 21.501286 | D44: V | E44: V_pico_DC − ΔV/2
A45: 38 | B45: Corriente DC máxima del bus (peor caso) | C45: =$C$22/$C$44 -> 8.2202218 | D45: A | E45: I = P_in_DC / V_media
A46: 39 | B46: Capacitancia mínima requerida del filtro | C46: =$C$45/(2*$C$6*$C$40)*1000000 -> 22833.95 | D46: µF | E46: C = I / (2·f·ΔV) (rectificación de onda completa) | F46: Fórmula estándar de filtro capacitivo
A47: 40 | B47: Capacitor elegido (unitario) | C47: 10000 | D47: µF | E47: Electrolítico snap-in 50 V. | F47: Nichicon LKS1H103MESB
A48: 41 | B48: Número de capacitores en paralelo | C48: 3 | E48: Para repartir la corriente de rizado. | F48: Decisión de diseño
A49: 42 | B49: Capacitancia total del bus | C49: =$C$47*$C$48 -> 30000 | D49: µF | E49: C_unit · N
A50: 43 | B50: Capacitancia suficiente | C50: =IF($C$49>=$C$46,"OK","REVISAR") -> OK | E50: C_total ≥ C_requerida
A51: 44 | B51: Rizado real del bus (pico a pico) | C51: =$C$45/(2*$C$6*$C$49/1000000) -> 2.283395 | D51: V | E51: ΔV = I / (2·f·C)
A52: 45 | B52: Tensión MÍNIMA del bus VIN DC (peor caso) | C52: =$C$43-$C$51 -> 20.717891 | D52: V | E52: Pico DC − rizado (red −10 %, plena carga, valle del rizado)
A53: 46 | B53: Tensión máxima de la salida variable | C53: 15 | D53: V | E53: Límite superior de la salida ajustable. | F53: Documento del proyecto (PDF) Tabla 1
A54: 47 | B54: Caída del diodo Schottky (referencia) | C54: 0.5 | D54: V | E54: Valor típico del fabricante. | F54: Hoja de datos LM2678 (TI, SNVS029L) §7.2.3
A55: 48 | B55: Ciclo de trabajo máximo del LM2678 | C55: 0.91 | E55: Limita la relación Vout/Vin mínima. | F55: Hoja de datos LM2678 (TI, SNVS029L) §5.9
A56: 49 | B56: Bus mínimo para que la salida variable alcance 15 V | C56: =($C$53+$C$54)/$C$55+Convertidores!$G$26-$C$54 -> 16.892967 | D56: V | E56: Vin = (Vout + Vd)/Dmax + Vsat − Vd
A57: 50 | B57: Entrada mínima del LM2678-12 | C57: 15 | D57: V | E57: La versión de 12 V exige Vin ≥ 15 V. | F57: Hoja de datos LM2678 (TI, SNVS029L) §5.7
A58: 51 | B58: Margen adicional sobre el mínimo del bus | C58: 1 | D58: V | E58: Colchón para tolerancias de componentes. | F58: Decisión de diseño
A59: 52 | B59: Tensión mínima REQUERIDA del bus VIN DC | C59: =MAX($C$56,$C$57)+$C$58 -> 17.892967 | D59: V | E59: máx(Vin_var, 15 V) + margen | F59: Dato pendiente del PDF
A60: 53 | B60: El bus cumple el mínimo requerido | C60: =IF($C$52>=$C$59,"OK","REVISAR") -> OK | E60: V_bus_min ≥ V_requerida
A61: 54 | B61: Tensión del secundario en vacío con red +10 % | C61: =$C$31*(1+$C$7) -> 22.77 | D61: V rms | E61: V_vacío · (1 + tol) | F61: Peor caso para el máximo del bus
A62: 55 | B62: Tensión de pico del secundario (red +10 %, vacío) | C62: =$C$61*SQRT(2) -> 32.201643 | D62: V | E62: V_rms · √2
A63: 56 | B63: Tensión MÁXIMA del bus VIN DC (peor caso) | C63: =$C$62-2*$C$39 -> 30.801643 | D63: V | E63: Pico − 2·VF (red +10 %, sin carga)
A64: 57 | B64: Entrada máxima recomendada de los LM2678 | C64: 40 | D64: V | E64: Rango de operación 8–40 V (máx. absoluto 45 V). | F64: Hoja de datos LM2678 (TI, SNVS029L) §5.1 y §5.3
A65: 58 | B65: El bus no supera el límite de los convertidores | C65: =IF($C$63<=$C$64,"OK","REVISAR") -> OK | E65: V_bus_max ≤ 40 V
A66: 59 | B66: Margen respecto a los 40 V | C66: =1-$C$63/$C$64 -> 0.22995893 | D66: % | E66: 1 − V_max/40
A67: 60 | B67: Tensión nominal de los capacitores del bus | C67: 50 | D67: V | E67: Electrolíticos de 50 V. | F67: Nichicon LKS1H103MESB
A68: 61 | B68: Relación tensión nominal / tensión máxima del bus | C68: =$C$67/$C$63 -> 1.62329 | D68: × | E68: Debe ser ≥ 1,25
A69: 62 | B69: Capacitores con margen de tensión | C69: =IF($C$68>=1.25,"OK","REVISAR") -> OK | E69: Relación ≥ 1,25
A70: 63 | B70: Tensión media del bus en condiciones nominales (red 120 V, plena carga) | C70: =$C$32*SQRT(2)-2*$C$38-$C$51/2 -> 24.659731 | D70: V | E70: V_pico − 2·VF − ΔV/2 | F70: Solo informativo
A71: 5. DIMENSIONAMIENTO DEL TRANSFORMADOR (¿cuál elegir?)
A72: 64 | B72: Factor corriente RMS del secundario / corriente DC | C72: 1.8 | D72: × | E72: En puente con filtro capacitivo la corriente RMS del secundario es ≈1,6–2,0 × I_DC. | F72: Regla práctica de diseño de fuentes lineales
A73: 65 | B73: Corriente RMS del secundario (peor caso) | C73: =$C$72*$C$45 -> 14.796399 | D73: A rms | E73: I_sec = k · I_DC_max
A74: 66 | B74: Potencia aparente que debe entregar el secundario | C74: =$C$27*$C$73 -> 295.92799 | D74: VA | E74: S = V_secundario · I_sec
A75: 67 | B75: Margen de seguridad de potencia | C75: 0.2 | E75: Evita operar el transformador al límite. | F75: Decisión de diseño
A76: 68 | B76: Potencia mínima del transformador | C76: =$C$74*(1+$C$75) -> 355.11358 | D76: VA | E76: S_req = S · (1 + margen)
A77: 69 | B77: Uso del Antek AS-3220 (300 VA, 2 × 20 V / 7,5 A) | C77: =$C$73/(7.5*$C$29) -> 0.98642662 | E77: I_sec / I_nominal_paralelo | F77: Antek AS-3220
A78: 70 | B78: AS-3220 con 20 % de margen | C78: =IF($C$77<=1/(1+$C$75),"Cumple","No cumple") -> No cumple | E78: Uso ≤ 83 %
A79: 71 | B79: Uso del Antek AS-4220 (400 VA, 2 × 20 V / 10 A) ← SELECCIONADO | C79: =$C$73/($C$28*$C$29) -> 0.73981996 | E79: I_sec / I_nominal_paralelo | F79: Hoja de datos Antek AS-4220
A80: 72 | B80: AS-4220 con 20 % de margen | C80: =IF($C$79<=1/(1+$C$75),"Cumple","No cumple") -> Cumple | E80: Uso ≤ 83 %
A81: 73 | B81: Uso del Antek AN-5220 (500 VA, 2 × 20 V / 12,5 A) | C81: =$C$73/(12.5*$C$29) -> 0.59185597 | E81: I_sec / I_nominal_paralelo | F81: Antek AN-5220
A82: 74 | B82: AN-5220 con 20 % de margen | C82: =IF($C$81<=1/(1+$C$75),"Cumple","No cumple") -> Cumple | E82: Uso ≤ 83 % (sobredimensionado, más caro y pesado)
A83: 75 | B83: Corriente de rizado RMS total en los capacitores del bus | C83: =SQRT($C$73^2-$C$45^2) -> 12.302901 | D83: A rms | E83: √(I_sec² − I_DC²)
A84: 76 | B84: Corriente de rizado por capacitor (verificar contra hoja de datos) | C84: =$C$83/$C$48 -> 4.1009672 | D84: A rms | E84: Debe ser ≤ corriente de rizado nominal del capacitor a 120 Hz / 105 °C | F84: Validar en hoja de datos LKS1H103MESB
A85: 77 | B85: Corriente DC del bus en condiciones nominales | C85: =$C$22/$C$70 -> 7.1673668 | D85: A | E85: P_in_DC / V_bus_nom
A86: 78 | B86: Potencia aparente del secundario en condiciones nominales | C86: =$C$32*$C$72*$C$85 -> 255.44495 | D86: VA | E86: V · k · I_DC
A87: 79 | B87: Potencia aparente del primario en condiciones nominales | C87: =$C$86/$C$35 -> 268.88942 | D87: VA | E87: S_sec / η_trafo
A88: 80 | B88: Corriente del primario en condiciones nominales | C88: =$C$87/$C$5 -> 2.2407452 | D88: A rms | E88: S_prim / V_red
A89: 81 | B89: Potencia aparente del secundario con red −10 % | C89: =$C$41*$C$73 -> 263.67184 | D89: VA | E89: V_sec_ll · I_sec
A90: 82 | B90: Corriente máxima del primario (red −10 %, plena carga) | C90: =$C$89/$C$35/$C$8 -> 2.5699009 | D90: A rms | E90: S_sec_ll / η / V_red_min
A91: 6. PROTECCIÓN DE ENTRADA (antes del transformador)
A92: 83 | B92: Corriente nominal mínima del fusible de entrada | C92: =$C$90/$C$17 -> 3.4265346 | D92: A | E92: I_primario_max / 0,75
A93: 84 | B93: Fusible de entrada seleccionado (acción lenta, 250 V) | C93: 4 | D93: A | E93: T4A: soporta el arranque del toroidal y el funcionamiento normal. | F93: Valor estándar de fusible
A94: 85 | B94: Fusible de entrada adecuado | C94: =IF($C$93>=$C$92,"OK","REVISAR") -> OK | E94: I_fusible ≥ I_requerida
A95: 86 | B95: NTC limitador de corriente de arranque (resistencia a 25 °C) | C95: 10 | D95: Ω | E95: Limita el pico de arranque del toroidal y de los 30 000 µF. | F95: Ametherm SL32 10015
A96: 87 | B96: Corriente máxima en régimen del NTC | C96: 15 | D96: A | E96: Dato del fabricante. | F96: Ametherm SL32 10015
A97: 88 | B97: Pico de arranque máximo admisible | C97: 20 | D97: A | E97: Para no fundir el fusible T4A en el encendido. | F97: Decisión de diseño
A98: 89 | B98: Pico de arranque estimado (NTC frío, red +10 %) | C98: =$C$9*SQRT(2)/$C$95 -> 18.667619 | D98: A | E98: V_pico_red / R_NTC
A99: 90 | B99: Arranque controlado | C99: =IF(AND($C$98<=$C$97,$C$96>=$C$90),"OK","REVISAR") -> OK | E99: I_pico ≤ 20 A e I_NTC ≥ I_primario
A100: 91 | B100: Varistor (MOV) — tensión AC continua máxima | C100: 150 | D100: V rms | E100: Debe superar la red máxima con margen. | F100: TDK EPCOS S14K150
...

Sheet Convertidores
A1: Diseño de los cinco convertidores DC/DC — cálculos por salida
A2: Metodología del fabricante (hoja de datos LM2678, §7.2: E·T, inductor, capacitores, diodo) y TPS54560B inversor (§8.3). Entradas en azul; todo lo demás son fórmulas.
A4: N.º | B4: Concepto | C4: +12 V / 5 A | D4: +5 V / 5 A | E4: +3,3 V / 3 A | F4: −12 V / 1 A | G4: Variable 1,25–15 V / 3 A | H4: Unidad | I4: Fundamento / fuente
A5: 1. DATOS DE LA SALIDA
A6: 1 | B6: Circuito integrado | C6: LM2678T-12 | D6: LM2678T-5.0 | E6: LM2678T-3.3 | F6: TPS54560B | G6: LM2678T-ADJ | I6: Candidatos del PDF validados contra su hoja de datos.
A7: 2 | B7: Topología | C7: Reductor (buck) | D7: Reductor (buck) | E7: Reductor (buck) | F7: Buck-boost inversor | G7: Reductor (buck) ajustable | I7: −12 V: TPS54560B en configuración inversora (hoja de datos §8.3 y nota SLVA317).
A8: 3 | B8: Tensión de salida (máxima para la variable) | C8: 12 | D8: 5 | E8: 3.3 | F8: -12 | G8: 15 | H8: V | I8: Tabla 1 del PDF.
A9: 4 | B9: Corriente máxima de salida | C9: 5 | D9: 5 | E9: 3 | F9: 1 | G9: 3 | H9: A | I9: Tabla 1 del PDF.
A10: 5 | B10: Potencia máxima de salida | C10: =ABS(C8)*C9 -> 60 | D10: =ABS(D8)*D9 -> 25 | E10: =ABS(E8)*E9 -> 9.9 | F10: =ABS(F8)*F9 -> 12 | G10: =ABS(G8)*G9 -> 45 | H10: W | I10: P = |V|·I
A11: 6 | B11: Eficiencia de diseño (conservadora) | C11: 0.9 | D11: 0.8 | E11: 0.78 | F11: 0.8 | G11: 0.88 | I11: LM2678 datasheet: 92 % (12 V, Vin 24 V), 84 % (5 V), 82 % (3,3 V) a Vin 12 V; se reduce porque aquí Vin ≈ 21–31 V. −12 V: supuesto.
A12: 7 | B12: Potencia tomada del bus VIN DC | C12: =C10/C11 -> 66.666667 | D12: =D10/D11 -> 31.25 | E12: =E10/E11 -> 12.692308 | F12: =F10/F11 -> 15 | G12: =G10/G11 -> 51.136364 | H12: W | I12: P_in = P_out / η
A13: 8 | B13: Pérdidas del convertidor | C13: =C12-C10 -> 6.6666667 | D13: =D12-D10 -> 6.25 | E13: =E12-E10 -> 2.7923077 | F13: =F12-F10 -> 3 | G13: =G12-G10 -> 6.1363636 | H13: W | I13: P_in − P_out
A14: 2. ENTRADA DESDE EL BUS VIN DC
A15: 9 | B15: Tensión mínima del bus | C15: =Calculos!$C$52 -> 20.717891 | D15: =Calculos!$C$52 -> 20.717891 | E15: =Calculos!$C$52 -> 20.717891 | F15: =Calculos!$C$52 -> 20.717891 | G15: =Calculos!$C$52 -> 20.717891 | H15: V | I15: Hoja Calculos §4
A16: 10 | B16: Tensión máxima del bus | C16: =Calculos!$C$63 -> 30.801643 | D16: =Calculos!$C$63 -> 30.801643 | E16: =Calculos!$C$63 -> 30.801643 | F16: =Calculos!$C$63 -> 30.801643 | G16: =Calculos!$C$63 -> 30.801643 | H16: V | I16: Hoja Calculos §4
A17: 11 | B17: Entrada mínima del IC | C17: 15 | D17: 8 | E17: 8 | F17: 4.5 | G17: 8 | H17: V | I17: LM2678-12: 15 V; resto de LM2678: 8 V; TPS54560B: 4,5 V.
A18: 12 | B18: Verificación entrada mínima | C18: =IF(C15>=C17,"OK","REVISAR") -> OK | D18: =IF(D15>=D17,"OK","REVISAR") -> OK | E18: =IF(E15>=E17,"OK","REVISAR") -> OK | F18: =IF(F15>=F17,"OK","REVISAR") -> OK | G18: =IF(G15>=G17,"OK","REVISAR") -> OK | I18: Vin_min ≥ Vin_min_IC
A19: 13 | B19: Tensión máxima vista por el IC | C19: =C16 -> 30.801643 | D19: =D16 -> 30.801643 | E19: =E16 -> 30.801643 | F19: =F16+ABS(F8) -> 42.801643 | G19: =G16 -> 30.801643 | H19: V | I19: Inversor: el IC ve Vin + |Vout|.
A20: 14 | B20: Entrada máxima del IC | C20: 40 | D20: 40 | E20: 40 | F20: 60 | G20: 40 | H20: V | I20: LM2678: 40 V de operación (45 V absolutos); TPS54560B: 60 V.
A21: 15 | B21: Verificación entrada máxima | C21: =IF(C19<=C20,"OK","REVISAR") -> OK | D21: =IF(D19<=D20,"OK","REVISAR") -> OK | E21: =IF(E19<=E20,"OK","REVISAR") -> OK | F21: =IF(F19<=F20,"OK","REVISAR") -> OK | G21: =IF(G19<=G20,"OK","REVISAR") -> OK | I21: Vin_max ≤ límite del IC
A22: 16 | B22: Margen de tensión | C22: =1-C19/C20 -> 0.22995893 | D22: =1-D19/D20 -> 0.22995893 | E22: =1-E19/E20 -> 0.22995893 | F22: =1-F19/F20 -> 0.28663929 | G22: =1-G19/G20 -> 0.22995893 | H22: % | I22: 1 − Vin_max / límite
A23: 3. CICLO DE TRABAJO
A24: 17 | B24: Caída del diodo Schottky | C24: 0.5 | D24: 0.5 | E24: 0.5 | F24: 0.5 | G24: 0.5 | H24: V | I24: Valor típico del fabricante.
A25: 18 | B25: Resistencia del interruptor interno | C25: 0.12 | D25: 0.12 | E25: 0.12 | F25: 0.092 | G25: 0.12 | H25: Ω | I25: LM2678: 0,12 Ω típ.; TPS54560B: 92 mΩ.
A26: 19 | B26: Caída en el interruptor a Imax | C26: =C25*C9 -> 0.6 | D26: =D25*D9 -> 0.6 | E26: =E25*E9 -> 0.36 | F26: =F25*F9 -> 0.092 | G26: =G25*G9 -> 0.36 | H26: V | I26: Vsat = Rds·Iout
A27: 20 | B27: Ciclo de trabajo máximo (Vin mínimo) | C27: =(ABS(C8)+C24)/(C15-C26+C24) -> 0.60626958 | D27: =(ABS(D8)+D24)/(D15-D26+D24) -> 0.26675862 | E27: =(ABS(E8)+E24)/(E15-E26+E24) -> 0.18218525 | F27: =ABS(F8)/(F15+ABS(F8)) -> 0.36677181 | G27: =(ABS(G8)+G24)/(G15-G26+G24) -> 0.74312404 | I27: Buck: D = (Vout+Vd)/(Vin−Vsat+Vd). Inversor: D = |Vo|/(Vin+|Vo|).
A28: 21 | B28: Ciclo de trabajo mínimo (Vin máximo) | C28: =(ABS(C8)+C24)/(C16-C26+C24) -> 0.40714434 | D28: =(ABS(D8)+D24)/(D16-D26+D24) -> 0.17914351 | E28: =(ABS(E8)+E24)/(E16-E26+E24) -> 0.12281184 | F28: =ABS(F8)/(F16+ABS(F8)) -> 0.28036307 | G28: =(ABS(G8)+G24)/(G16-G26+G24) -> 0.50094302 | I28: Misma fórmula con Vin máximo.
A29: 22 | B29: Ciclo de trabajo máximo del IC | C29: 0.91 | D29: 0.91 | E29: 0.91 | F29: — | G29: 0.91 | I29: LM2678: 91 %.
A30: 23 | B30: Verificación del ciclo | C30: =IF(C27<=C29,"OK","REVISAR") -> OK | D30: =IF(D27<=D29,"OK","REVISAR") -> OK | E30: =IF(E27<=E29,"OK","REVISAR") -> OK | F30: — | G30: =IF(G27<=G29,"OK","REVISAR") -> OK | I30: D_max ≤ D_límite
A31: 4. INDUCTOR
A32: 24 | B32: Frecuencia de conmutación | C32: 260 | D32: 260 | E32: 260 | F32: 400 | G32: 260 | H32: kHz | I32: LM2678: 260 kHz fijos. TPS54560B: 400 kHz (valor de diseño; RT se fija con la ecuación del datasheet en el esquemático).
A33: 25 | B33: Constante E·T (voltios-microsegundo) | C33: =(C16-C26-ABS(C8))*(ABS(C8)+C24)/(C16-C26+C24)*1000/C32 -> 28.502676 | D33: =(D16-D26-ABS(D8))*(ABS(D8)+D24)/(D16-D26+D24)*1000/D32 -> 17.364272 | E33: =(E16-E26-ABS(E8))*(ABS(E8)+E24)/(E16-E26+E24)*1000/E32 -> 12.820442 | F33: — | G33: =(G16-G26-ABS(G8))*(ABS(G8)+G24)/(G16-G26+G24)*1000/G32 -> 29.751474 | H33: V·µs | I33: Ecuación (3) del datasheet LM2678.
A34: 26 | B34: Inductancia mínima (rizado ≤ 30 %) | C34: =C33/(Calculos!$C$14*C9) -> 19.001784 | D34: =D33/(Calculos!$C$14*D9) -> 11.576181 | E34: =E33/(Calculos!$C$14*E9) -> 14.244936 | F34: — | G34: =G33/(Calculos!$C$14*G9) -> 33.057193 | H34: µH | I34: L ≥ E·T / (0,3·Iout)
A35: 27 | B35: Inductancia seleccionada | C35: 22 | D35: 22 | E35: 22 | F35: 33 | G35: 47 | H35: µH | I35: Valores de la Tabla 7-3 del LM2678. ADJ: 33–47 µH recomendados para tensiones bajas.
A36: 28 | B36: Rizado de corriente del inductor (pico a pico) | C36: =C33/C35 -> 1.2955762 | D36: =D33/D35 -> 0.78928509 | E36: =E33/E35 -> 0.58274738 | F36: =F15*F27/(F32*1000*F35*0.000001) -> 0.57566199 | G36: =G33/G35 -> 0.63301008 | H36: A | I36: Buck: E·T/L (Vin máx). Inversor: Vin·D/(f·L) (Vin mín).
A37: 29 | B37: Corriente media del inductor | C37: =C9 -> 5 | D37: =D9 -> 5 | E37: =E9 -> 3 | F37: =F9/(1-F27) -> 1.5792095 | G37: =G9 -> 3 | H37: A | I37: Inversor: Iout/(1−D).
A38: 30 | B38: Corriente pico del inductor | C38: =C37+C36/2 -> 5.6477881 | D38: =D37+D36/2 -> 5.3946425 | E38: =E37+E36/2 -> 3.2913737 | F38: =F37+F36/2 -> 1.8670405 | G38: =G37+G36/2 -> 3.316505 | H38: A | I38: I_prom + ΔI/2
A39: 31 | B39: Corriente nominal del inductor elegido | C39: 5.22 | D39: 5.22 | E39: 5.22 | F39: 4.26 | G39: 3.57 | H39: A | I39: Tabla 7-3 LM2678 (L41, L40, L39).
A40: 32 | B40: Verificación del inductor | C40: =IF(AND(C35>=C34,C38<=C39),"OK","REVISAR") -> REVISAR | D40: =IF(AND(D35>=D34,D38<=D39),"OK","REVISAR") -> REVISAR | E40: =IF(AND(E35>=E34,E38<=E39),"OK","REVISAR") -> OK | F40: =IF(F38<=F39,"OK","REVISAR") -> OK | G40: =IF(AND(G35>=G34,G38<=G39),"OK","REVISAR") -> OK | I40: L ≥ L_min e I_pico ≤ I_nominal
A41: 33 | B41: Referencia del inductor | C41: Renco RL-1283-22-43 (L41) | D41: Renco RL-1283-22-43 (L41) | E41: Renco RL-1283-22-43 (L41) | F41: Pulse PE-54040 / Renco RL-1283-33-43 (L40) | G41: Pulse PE-54039 / Renco RL-5472-3 (L39) | I41: Referencias de la Tabla 7-3 del datasheet LM2678.
A42: 5. CAPACIDAD DE CORRIENTE DE SALIDA
A43: 34 | B43: Límite de corriente mínimo garantizado del IC | C43: 5.75 | D43: 5.75 | E43: 5.75 | F43: 5 | G43: 5.75 | H43: A | I43: LM2678: 5,75 A mín. (−40…125 °C). TPS54560B: 5 A (valor conservador).
A44: 35 | B44: Corriente máxima entregable | C44: =C43-C36/2 -> 5.1022119 | D44: =D43-D36/2 -> 5.3553575 | E44: =E43-E36/2 -> 5.4586263 | F44: =(F43-F36/2)*(1-F27) -> 2.9838782 | G44: =G43-G36/2 -> 5.433495 | H44: A | I44: Buck: I_lim − ΔI/2. Inversor: (I_lim − ΔI/2)·(1−D).
A45: 36 | B45: Verificación de capacidad | C45: =IF(C44>=C9,"OK","REVISAR") -> OK | D45: =IF(D44>=D9,"OK","REVISAR") -> OK | E45: =IF(E44>=E9,"OK","REVISAR") -> OK | F45: =IF(F44>=F9,"OK","REVISAR") -> OK | G45: =IF(G44>=G9,"OK","REVISAR") -> OK | I45: I_entregable ≥ Imax
A46: 6. CAPACITOR DE SALIDA Y RIZADO
A47: 37 | B47: Capacitancia de salida total | C47: 560 | D47: 560 | E47: 1000 | F47: 100 | G47: 1120 | H47: µF | I47: Tablas 7-6 y 7-10 del LM2678 (Panasonic HFQ). Variable: 2 × 560 µF cubre 1,25–15 V.
A48: 38 | B48: Tensión nominal del capacitor de salida | C48: 35 | D48: 35 | E48: 35 | F48: 25 | G48: 35 | H48: V | I48: Debe ser ≥ 1,3 × Vout.
A49: 39 | B49: Verificación de tensión | C49: =IF(C48>=1.3*ABS(C8),"OK","REVISAR") -> OK | D49: =IF(D48>=1.3*ABS(D8),"OK","REVISAR") -> OK | E49: =IF(E48>=1.3*ABS(E8),"OK","REVISAR") -> OK | F49: =IF(F48>=1.3*ABS(F8),"OK","REVISAR") -> OK | G49: =IF(G48>=1.3*ABS(G8),"OK","REVISAR") -> OK | I49: V_cap ≥ 1,3·Vout
A50: 40 | B50: ESR estimada del capacitor de salida | C50: 0.06 | D50: 0.06 | E50: 0.05 | F50: 0.05 | G50: 0.03 | H50: Ω | I50: Supuesto — validar con la hoja de datos del capacitor elegido.
A51: 41 | B51: Rizado de salida estimado (pico a pico) | C51: =C36*C50 -> 0.077734571 | D51: =D36*D50 -> 0.047357105 | E51: =E36*E50 -> 0.029137369 | F51: =F38*F50+F9*F27/(F32*1000*F47*0.000001) -> 0.10252132 | G51: =G36*G50 -> 0.018990302 | H51: V | I51: Buck: ΔI·ESR. Inversor: Ipk·ESR + Iout·D/(f·C).
A52: 42 | B52: Rizado relativo | C52: =C51/ABS(C8) -> 0.0064778809 | D52: =D51/ABS(D8) -> 0.0094714211 | E52: =E51/ABS(E8) -> 0.0088295058 | F52: =F51/ABS(F8) -> 0.0085434435 | G52: =G51/ABS(G8) -> 0.0012660202 | H52: % | I52: Rizado / |Vout|
A53: 43 | B53: Verificación del rizado | C53: =IF(C52<=Calculos!$C$13,"OK","REVISAR") -> OK | D53: =IF(D52<=Calculos!$C$13,"OK","REVISAR") -> OK | E53: =IF(E52<=Calculos!$C$13,"OK","REVISAR") -> OK | F53: =IF(F52<=Calculos!$C$13,"OK","REVISAR") -> OK | G53: =IF(G52<=Calculos!$C$13,"OK","REVISAR") -> OK | I53: Rizado ≤ 1 % de Vout
A54: 44 | B54: Capacitor de salida elegido | C54: 1 × 560 µF/35 V low-ESR (HFQ C5) | D54: 1 × 560 µF/35 V low-ESR (HFQ C5) | E54: 1 × 1000 µF/35 V low-ESR (HFQ C7) | F54: 1 × 100 µF/25 V low-ESR + 2 × 10 µF/25 V X7R | G54: 2 × 560 µF/35 V low-ESR (HFQ C5) | I54: Equivalentes vigentes de la serie Panasonic HFQ indicada por TI.
A55: 7. CAPACITOR DE ENTRADA LOCAL (junto a cada convertidor)
A56: 45 | B56: Capacitancia de entrada | C56: 1500 | D56: 1500 | E56: 1500 | F56: 100 | G56: 1500 | H56: µF | I56: LM2678: 1500 µF/63 V (Tabla 7-8, código C16). TPS54560B: 100 µF + cerámicos.
A57: 46 | B57: Tensión nominal | C57: 63 | D57: 63 | E57: 63 | F57: 63 | G57: 63 | H57: V | I57: Debe ser ≥ 1,3 × Vin máx.
A58: 47 | B58: Corriente RMS requerida | C58: =C9/2 -> 2.5 | D58: =D9/2 -> 2.5 | E58: =E9/2 -> 1.5 | F58: =F37*SQRT(F27*(1-F27)) -> 0.76105817 | G58: =G9/2 -> 1.5 | H58: A | I58: Buck: Iout/2. Inversor: I_L·√(D(1−D)).
A59: 48 | B59: Corriente RMS nominal del capacitor | C59: 2.51 | D59: 2.51 | E59: 2.51 | F59: 1 | G59: 2.51 | H59: A | I59: HFQ C16: 2,51 A (datasheet LM2678). TPS54560B: supuesto — validar.
A60: 49 | B60: Verificación | C60: =IF(AND(C57>=1.3*C19,C59>=C58),"OK","REVISAR") -> OK | D60: =IF(AND(D57>=1.3*D19,D59>=D58),"OK","REVISAR") -> OK | E60: =IF(AND(E57>=1.3*E19,E59>=E58),"OK","REVISAR") -> OK | F60: =IF(AND(F57>=1.3*F19,F59>=F58),"OK","REVISAR") -> OK | G60: =IF(AND(G57>=1.3*G19,G59>=G58),"OK","REVISAR") -> OK | I60: V ≥ 1,3·Vin_máx e I_rms ≥ requerida
A61: 8. DIODO DE LIBRE CIRCULACIÓN (Schottky)
A62: 50 | B62: Diodo elegido | C62: MBR745 | D62: MBR745 | E62: MBR745 | F62: SS36 | G62: MBR745 | I62: MBR745: Tabla 7-4 del LM2678 (7,5 A, 45 V). SS36: 3 A, 60 V.
A63: 51 | B63: Tensión inversa | C63: 45 | D63: 45 | E63: 45 | F63: 60 | G63: 45 | H63: V | I63: Debe ser ≥ 1,3 × Vin máx.
A64: 52 | B64: Corriente media nominal | C64: 7.5 | D64: 7.5 | E64: 7.5 | F64: 3 | G64: 7.5 | H64: A | I64: Debe superar la corriente pico del inductor.
A65: 53 | B65: Verificación del diodo | C65: =IF(AND(C63>=1.3*C19,C64>=C38),"OK","REVISAR") -> OK | D65: =IF(AND(D63>=1.3*D19,D64>=D38),"OK","REVISAR") -> OK | E65: =IF(AND(E63>=1.3*E19,E64>=E38),"OK","REVISAR") -> OK | F65: =IF(AND(F63>=1.3*F19,F64>=F38),"OK","REVISAR") -> OK | G65: =IF(AND(G63>=1.3*G19,G64>=G38),"OK","REVISAR") -> OK | I65: V_R ≥ 1,3·Vin y I_F ≥ I_pico
A66: 54 | B66: Potencia disipada en el diodo | C66: =C24*C9*(1-C28) -> 1.4821392 | D66: =D24*D9*(1-D28) -> 2.0521412 | E66: =E24*E9*(1-E28) -> 1.3157822 | F66: =F24*F9 -> 0.5 | G66: =G24*G9*(1-(Calculos!$C$132+G24)/(G16-G26+G24)) -> 1.415204 | H66: W | I66: Vd·Iout·(1−D). Variable: peor caso a Vout mínimo.
A67: 9. VERIFICACIÓN TÉRMICA DEL CONVERTIDOR
A68: 55 | B68: Encapsulado y disipación | C68: TO-220-7 + disipador | D68: TO-220-7 + disipador | E68: TO-220-7 + disipador | F68: HSOIC-8 PowerPAD (DDA) sobre cobre | G68: TO-220-7 + disipador | I68: El LM2678 TO-220 queda en el plano de tierra (pestaña a GND).
A69: 56 | B69: Fracción de las pérdidas que se disipan en el IC | C69: 0.6 | D69: 0.6 | E69: 0.6 | F69: 0.6 | G69: 0.6 | I69: El resto se reparte entre diodo e inductor.
A70: 57 | B70: Potencia disipada en el IC | C70: =C69*C13 -> 4 | D70: =D69*D13 -> 3.75 | E70: =E69*E13 -> 1.6753846 | F70: =F69*F13 -> 1.8 | G70: =G69*G13 -> 3.6818182 | H70: W | I70: P_IC = fracción · pérdidas
A71: 58 | B71: Resistencia térmica unión–cápsula (TO-220) | C71: 2 | D71: 2 | E71: 2 | F71: — | G71: 2 | H71: °C/W | I71: LM2678 datasheet §5.4.
A72: 59 | B72: Resistencia cápsula–disipador | C72: 1 | D72: 1 | E72: 1 | F72: — | G72: 1 | H72: °C/W | I72: Con grasa térmica (supuesto).
A73: 60 | B73: Resistencia térmica máxima del disipador | C73: =(Calculos!$C$11-Calculos!$C$10)/C70-C71-C72 -> 18.25 | D73: =(Calculos!$C$11-Calculos!$C$10)/D70-D71-D72 -> 19.666667 | E73: =(Calculos!$C$11-Calculos!$C$10)/E70-E71-E72 -> 47.734619 | F73: — | G73: =(Calculos!$C$11-Calculos!$C$10)/G70-G71-G72 -> 20.08642 | H73: °C/W | I73: Rθsa ≤ (Tj − Tamb)/P − Rθjc − Rθcs
A74: 61 | B74: Disipador seleccionado | C74: 12 | D74: 12 | E74: 12 | F74: — | G74: 12 | H74: °C/W | I74: Disipador estándar para TO-220 (≤ 12 °C/W).
A75: 62 | B75: Resistencia térmica unión–ambiente | C75: — | D75: — | E75: — | F75: 40 | G75: — | H75: °C/W | I75: Supuesto para HSOIC-8 PowerPAD sobre cobre — validar con el datasheet y el layout.
A76: 63 | B76: Temperatura de unión estimada | C76: =Calculos!$C$10+C70*(C71+C72+C74) -> 100 | D76: =Calculos!$C$10+D70*(D71+D72+D74) -> 96.25 | E76: =Calculos!$C$10+E70*(E71+E72+E74) -> 65.130769 | F76: =Calculos!$C$10+F70*F75 -> 112 | G76: =Calculos!$C$10+G70*(G71+G72+G74) -> 95.227273 | H76: °C | I76: Tj = Tamb + P·Rθ_total
A77: 64 | B77: Verificación térmica | C77: =IF(C76<=Calculos!$C$11,"OK","REVISAR") -> OK | D77: =IF(D76<=Calculos!$C$11,"OK","REVISAR") -> OK | E77: =IF(E76<=Calculos!$C$11,"OK","REVISAR") -> OK | F77: =IF(F76<=Calculos!$C$11,"OK","REVISAR") -> OK | G77: =IF(G76<=Calculos!$C$11,"OK","REVISAR") -> OK | I77: Tj ≤ 125 °C
A78: 10. PROTECCIÓN DE CADA SALIDA
A79: 65 | B79: Corriente de retención mínima del PTC | C79: =C9*Calculos!$C$16/Calculos!$C$15-0.000000001 -> 7 | D79: =D9*Calculos!$C$16/Calculos!$C$15-0.000000001 -> 7 | E79: =E9*Calculos!$C$16/Calculos!$C$15-0.000000001 -> 4.2 | F79: =F9*Calculos!$C$16/Calculos!$C$15-0.000000001 -> 1.4 | G79: =G9*Calculos!$C$16/Calculos!$C$15-0.000000001 -> 4.2 | H79: A | I79: Imax · margen / factor de reducción
A80: 66 | B80: Posición en la tabla de PTC (auxiliar) | C80: =IFERROR(MATCH(C79,$C$90:$C$100,1),0) -> 9 | D80: =IFERROR(MATCH(D79,$C$90:$C$100,1),0) -> 9 | E80: =IFERROR(MATCH(E79,$C$90:$C$100,1),0) -> 7 | F80: =IFERROR(MATCH(F79,$C$90:$C$100,1),0) -> 2 | G80: =IFERROR(MATCH(G79,$C$90:$C$100,1),0) -> 7 | I80: Auxiliar de cálculo.
A81: 67 | B81: Índice del PTC elegido (auxiliar) | C81: =IF(C80=0,1,IF(INDEX($C$90:$C$100,C80)>=C79,C80,C80+1)) -> 10 | D81: =IF(D80=0,1,IF(INDEX($C$90:$C$100,D80)>=D79,D80,D80+1)) -> 10 | E81: =IF(E80=0,1,IF(INDEX($C$90:$C$100,E80)>=E79,E80,E80+1)) -> 8 | F81: =IF(F80=0,1,IF(INDEX($C$90:$C$100,F80)>=F79,F80,F80+1)) -> 3 | G81: =IF(G80=0,1,IF(INDEX($C$90:$C$100,G80)>=G79,G80,G80+1)) -> 8 | I81: Primer PTC con retención suficiente.
A82: 68 | B82: PTC reiniciable seleccionado (Bourns) | C82: =INDEX($B$90:$B$100,C81) -> MF-R700 | D82: =INDEX($B$90:$B$100,D81) -> MF-R700 | E82: =INDEX($B$90:$B$100,E81) -> MF-R500 | F82: =INDEX($B$90:$B$100,F81) -> MF-R160 | G82: =INDEX($B$90:$B$100,G81) -> MF-R500 | I82: Serie MF-R, radial. Retención y disparo: ver tabla al final.
A83: 69 | B83: Corriente de retención del PTC | C83: =INDEX($C$90:$C$100,C81) -> 7 | D83: =INDEX($C$90:$C$100,D81) -> 7 | E83: =INDEX($C$90:$C$100,E81) -> 5 | F83: =INDEX($C$90:$C$100,F81) -> 1.6 | G83: =INDEX($C$90:$C$100,G81) -> 5 | H83: A | I83: A 23 °C.
A84: 70 | B84: Verificación del PTC | C84: =IF(C83*Calculos!$C$15>=C9,"OK","REVISAR") -> OK | D84: =IF(D83*Calculos!$C$15>=D9,"OK","REVISAR") -> OK | E84: =IF(E83*Calculos!$C$15>=E9,"OK","REVISAR") -> OK | F84: =IF(F83*Calculos!$C$15>=F9,"OK","REVISAR") -> OK | G84: =IF(G83*Calculos!$C$15>=G9,"OK","REVISAR") -> OK | I84: Retención derateada ≥ Imax
A85: 71 | B85: Diodo de sujeción en el borne de salida | C85: SMCJ13A (TVS 1500 W) | D85: SMCJ6.0A (TVS 1500 W) | E85: Zener 1N5335B (3,9 V, 5 W) | F85: SMCJ13CA (TVS bidireccional) | G85: SMCJ16A (TVS 1500 W) | I85: Recorta sobretensiones y picos inductivos.
A86: 72 | B86: Tensión de trabajo (Vwm) / Zener (Vz) | C86: 13 | D86: 6 | E86: 3.9 | F86: 13 | G86: 16 | H86: V | I86: No debe conducir con Vout máxima.
A87: 73 | B87: Tensión de sujeción máxima (Vc / Vz máx.) | C87: 21.5 | D87: 10.3 | E87: 4.1 | F87: 21.5 | G87: 26 | H87: V | I87: Valores de hoja de datos de la serie SMCJ (validar).
A88: 74 | B88: Verificación del TVS | C88: =IF(C86>=ABS(C8)*(1+Calculos!$C$12),"OK","REVISAR") -> OK | D88: =IF(D86>=ABS(D8)*(1+Calculos!$C$12),"OK","REVISAR") -> OK | E88: =IF(E86>=ABS(E8)*(1+Calculos!$C$12),"OK","REVISAR") -> OK | F88: =IF(F86>=ABS(F8)*(1+Calculos!$C$12),"OK","REVISAR") -> OK | G88: =IF(G86>=ABS(G8)*(1+Calculos!$C$12),"OK","REVISAR") -> OK | I88: Vwm ≥ Vout·(1 + tolerancia)
A89: 11. TABLA DE REFERENCIA: PTC REINICIABLES BOURNS MF-R (retención ascendente)
B90: MF-R110 | C90: 1.1 | D90: 2.2 | H90: A | I90: Retención (col. C) y disparo = 2 × retención (col. D). Bourns MF-R, hoja de datos mf-r.pdf.
B91: MF-R135 | C91: 1.35 | D91: 2.7 | H91: A | I91: Retención (col. C) y disparo = 2 × retención (col. D). Bourns MF-R, hoja de datos mf-r.pdf.
B92: MF-R160 | C92: 1.6 | D92: 3.2 | H92: A | I92: Retención (col. C) y disparo = 2 × retención (col. D). Bourns MF-R, hoja de datos mf-r.pdf.
B93: MF-R185 | C93: 1.85 | D93: 3.7 | H93: A | I93: Retención (col. C) y disparo = 2 × retención (col. D). Bourns MF-R, hoja de datos mf-r.pdf.
B94: MF-R250 | C94: 2.5 | D94: 5 | H94: A | I94: Retención (col. C) y disparo = 2 × retención (col. D). Bourns MF-R, hoja de datos mf-r.pdf.
B95: MF-R300 | C95: 3 | D95: 6 | H95: A | I95: Retención (col. C) y disparo = 2 × retención (col. D). Bourns MF-R, hoja de datos mf-r.pdf.
B96: MF-R400 | C96: 4 | D96: 8 | H96: A | I96: Retención (col. C) y disparo = 2 × retención (col. D). Bourns MF-R, hoja de datos mf-r.pdf.
B97: MF-R500 | C97: 5 | D97: 10 | H97: A | I97: Retención (col. C) y disparo = 2 × retención (col. D). Bourns MF-R, hoja de datos mf-r.pdf.
B98: MF-R600 | C98: 6 | D98: 12 | H98: A | I98: Retención (col. C) y disparo = 2 × retención (col. D). Bourns MF-R, hoja de datos mf-r.pdf.
B99: MF-R700 | C99: 7 | D99: 14 | H99: A | I99: Retención (col. C) y disparo = 2 × retención (col. D). Bourns MF-R, hoja de datos mf-r.pdf.
B100: MF-R800 | C100: 8 | D100: 16 | H100: A | I100: Retención (col. C) y disparo = 2 × retención (col. D). Bourns MF-R, hoja de datos mf-r.pdf.

Sheet Decisiones
A1: Datos pendientes del PDF (§9) — resueltos
A2: Cada dato que el documento dejaba «por definir» tiene aquí su decisión, su valor y su justificación. La última columna marca lo que conviene validar con el docente.
A3: ID | B3: Dato pendiente (PDF §9) | C3: Decisión | D3: Valor | E3: Unidad | F3: Justificación / cálculo | G3: ¿Confirmar con el docente?
A4: D-01 | B4: Transformador: tensión del secundario | C4: Antek AS-4220, secundarios en paralelo | D4: =Calculos!$C$27 -> 20 | E4: V rms | F4: Con 20 V el bus nunca baja de la tensión requerida (Calculos §4) y nunca supera los 40 V de los LM2678. | G4: No
A5: D-02 | B5: Transformador: corriente nominal | C5: Secundarios 2 × 10 A en paralelo | D5: =Calculos!$C$30 -> 20 | E5: A rms | F5: La corriente RMS requerida es menor (Calculos §5). | G5: No
A6: D-03 | B6: Transformador: potencia | C6: Transformador de 400 VA | D6: =Calculos!$C$26 -> 400 | E6: VA | F6: Potencia mínima con margen del 20 %: ver Calculos §5. El AS-3220 (300 VA) queda al límite; el AN-5220 (500 VA) es innecesario. | G6: No
A7: D-04 | B7: Tensión mínima del bus VIN DC | C7: Mínimo requerido y mínimo obtenido | D7: =Calculos!$C$59 -> 17.892967 | E7: V | F7: Requerido (LM2678-12 y salida variable a 15 V + margen). El valor obtenido en el peor caso está en Calculos §4. | G7: No
A8: D-05 | B8: Rizado admisible del bus | C8: Rizado pico a pico máximo | D8: =Calculos!$C$40 -> 3 | E8: V | F8: Define C ≥ I/(2·f·ΔV). Con 30 000 µF el rizado real es menor (Calculos §4). | G8: No
A9: D-06 | B9: ¿Todas las salidas a corriente máxima a la vez? | C9: SÍ — se diseña para el peor caso | D9: =Calculos!$C$22 -> 176.74534 | E9: W | F9: Potencia al bus con las cinco salidas a plena carga, incluyendo pérdidas. | G9: Sí
A10: D-07 | B10: Tolerancia de regulación de cada salida | C10: ±3 % (carga y temperatura) | D10: =Calculos!$C$12 -> 0.03 | E10: ±% | F10: Especificación del LM2678 (±2 % a 25 °C). | G10: No
A11: D-08 | B11: Rizado de cada salida | C11: ≤ 1 % de Vout (pico a pico) | D11: =Calculos!$C$13 -> 0.01 | E11: % de Vout | F11: Criterio del fabricante; verificado en Convertidores §6. | G11: No
A12: D-09 | B12: Topología del convertidor de −12 V | C12: Buck-boost inversor con TPS54560B | D12: Inversor | F12: La hoja de datos del TPS54560B incluye la sección «Inverting Power» (§8.3) y la nota SLVA317. Vin del IC = Vbus + 12 V < 60 V. | G12: No
A13: D-10 | B13: Protección de entrada: tipo y umbrales | C13: Fusible T4A + varistor 150 Vac + NTC 10 Ω | D13: =Calculos!$C$93 -> 4 | E13: A | F13: Fusible ≥ I_primario/0,75; NTC limita el arranque (Calculos §6). | G13: No
A14: D-11 | B14: Protección del bus DC: tipo y umbrales | C14: Fusible ATO 15 A + TVS SMCJ30A + sangrado | D14: =Calculos!$C$118 -> 15 | E14: A | F14: Fusible ≥ I_DC/0,75; el TVS no conduce con el bus máximo (Calculos §8). | G14: No
A15: D-12 | B15: Protección de salidas: tipo y umbrales | C15: PTC Bourns MF-R + diodo de sujeción por salida | D15: Ver hoja | F15: Retención derateada ≥ 1,05·Imax; Vwm del TVS ≥ Vout·1,03 (Convertidores §10). | G15: No
A16: D-13 | B16: Eficiencia objetivo | C16: Total ≥ 70 %; DC/DC ≥ 80 % | D16: =Calculos!$C$140 -> 0.7 | F16: Eficiencia total calculada en Calculos §10. | G16: No
A17: D-14 | B17: Referencia común (tierra) | C17: GND común a las cinco salidas; flotante respecto a PE | D17: GND común | F17: El transformador aísla la red; el chasis va a PE; puente opcional GND–chasis. | G17: Sí
A18: D-15 | B18: Ubicación de la etapa de red | C18: Módulo IEC, fusible, interruptor, NTC y varistor cableados en el chasis | D18: Fuera de PCB | F18: La PCB trabaja solo con baja tensión (secundario). | G18: Sí
A19: D-16 | B19: Tensión y frecuencia de red | C19: 120 V / 60 Hz (Colombia) | D19: =Calculos!$C$5 -> 120 | E19: V rms | F19: Base de todos los cálculos del bus. | G19: Sí
